{
  "id": "mt-cap-479-mlt",
  "type": "statute",
  "title": "Att biex jiġu stabbiliti Ibħra tas-Sajd u Ġurisdizzjoni Marittima Estiża",
  "title_en": "Att biex jiġu stabbiliti Ibħra tas-Sajd u Ġurisdizzjoni Marittima Estiża",
  "short_name": "Kap. 479",
  "status": "in_force",
  "issued_date": "2010-07-22",
  "in_force_date": "2005-07-26",
  "url": "https://legislation.mt/eli/cap/479/20050726/mlt",
  "description": "Official text from legislation.mt (eli/cap/479/mlt, expression eli/cap/479/20050726/mlt).",
  "provisions": [
    {
      "provision_ref": "s1",
      "section": "1",
      "title": "L-ATT X tal-2005",
      "content": "It-titolu fil-qosor ta’ dan l-Att hu l-Att biex jiġu stabbiliti\nIbħra tas-Sajd u Ġurisdizzjoni Marittima Estiża.",
      "metadata": {
        "source_line_start": 16,
        "source_line_end": 21
      }
    },
    {
      "provision_ref": "s2",
      "section": "2",
      "title": "Titolu fil-qosor",
      "content": "(1) Bla ħsara għas-subartikolu (2), il-Prim Ministru jista’\nb’Ordni pubblikat fil-Gazzetta jiddikjara drittijiet sovrani għal\nMalta, bil-għan li jiġu esplorati u esplojtati, konservati u maniġġati\nfihom ir-riżorsi naturali li jgħixu u, jew li ma jgħixux, fil-medda ta’\ndawk iż-żoni tal-ibħra marittimi lil hinn mil-limiti stabbiliti flartikolu 3(2) tal-Att dwar l-Ibħra Territorjali u ż-Żona Kontigwa\nskont ma jista’ jiġi msemmi fl-Ordni u malli dan, iż-żoni hekk\nimsemmija għandhom ikunu jagħmlu parti mill-ibħra tas-sajd ta’\nMalta skont ma hemm provdut fl-artikolu 3(ċ) tal-Att dwar ilKonservazzjoni u l-Amministrazzjoni tas-Sajd.\n\nDrittijiet sovrani\nfuq ibħra tas-sajd\nstabbiliti.\n\n(2) Il-Prim Ministru jista’ ukoll b’Ordni li jiġi pubblikat filGazzetta jipprovdi dwar l-eżerċizzju tal-ġurisdizzjoni lil hinn millibħra territorjali ta’ Malta dwar (a) meta jsiru u jiġu wżati\nstallazzjonijiet u strutturi;\n\ngżejjer\n\nartifiċjali,\n\n(b) ir-riċerka marittima xjentifika; u\n(ċ) il-protezzjoni\nmarittimu.\n\nu\n\nl-preservazzjoni\n\ntal-ambjent\n\n(3) Ordni li jsir taħt dan l-artikolu jista’ jkun fih dawk ilpattijiet u l-kondizzjonijiet li l-Prim Ministru jista’ jqis li jkunu\nadatti.\n\nKap. 226.\n\nKap. 425.",
      "metadata": {
        "source_line_start": 22,
        "source_line_end": 60
      }
    }
  ],
  "definitions": []
}
