{
  "id": "mt-sl-325-4-mlt",
  "type": "statute",
  "title": "Ordni dwar Kumpanniji li jipprovdu Servizzi għall-Esportazzjoni Kwalifikanti (L-Ogħla Kera li jintalab)Imħassar bl-Avviż Legali 421 tal-2014",
  "title_en": "Ordni dwar Kumpanniji li jipprovdu Servizzi għall-Esportazzjoni Kwalifikanti (L-Ogħla Kera li jintalab)Imħassar bl-Avviż Legali 421 tal-2014",
  "short_name": "eli/sl/325.4/mlt",
  "status": "in_force",
  "issued_date": "2010-07-22",
  "in_force_date": "2010-07-22",
  "url": "https://legislation.mt/eli/sl/325.4/20100722/mlt",
  "description": "Official text from legislation.mt (eli/sl/325.4/mlt, expression eli/sl/325.4/20100722/mlt).",
  "provisions": [
    {
      "provision_ref": "s1",
      "section": "1",
      "title": "Full text",
      "content": "KUMPANNIJI LI JIPPROVDU SERVIZZI KWALIFIKANTI\n(L-OG}LA KERA LI JINTALAB)\n\n[ L.S.325.04\n\nLE{ISLAZZJONI SUSSIDJARJA 325.04\nORDNI DWAR KUMPANNIJI\nLI JIPPROVDU SERVIZZI KWALIFIKANTI\n(L-OG}LA KERA LI JINTALAB)\n1 ta’ Jannar, 1998\nL-AVVI| LEGALI 21 tal-1998, kif emendat bl-Avvi\\ Legali 424 tal-2007.\n\nRevokat bl-Avviż Legali 421 tal-2014.\n\n1",
      "metadata": {
        "extraction_mode": "fallback_full_text"
      }
    }
  ],
  "definitions": []
}
