{
  "id": "mt-sl-549-43-mlt",
  "type": "statute",
  "title": "Regolamenti dwar l-Ippakkjar u l-Iskart tal-Ippakkjar fil-Maniġġar tal-Iskart",
  "title_en": "Regolamenti dwar l-Ippakkjar u l-Iskart tal-Ippakkjar fil-Maniġġar tal-Iskart",
  "short_name": "eli/sl/549.43/mlt",
  "status": "in_force",
  "issued_date": "2010-12-21",
  "in_force_date": "2007-03-01",
  "url": "https://legislation.mt/eli/sl/549.43/20241206/mlt",
  "description": "Official text from legislation.mt (eli/sl/549.43/mlt, expression eli/sl/549.43/20241206/mlt).",
  "provisions": [
    {
      "provision_ref": "s1",
      "section": "1",
      "title": "1 ta’ Marzu, 2007",
      "content": "It-titolu ta’ dawn ir-regolamenti hu Regolamenti dwar lIppakkjar u l-Iskart tal-Ippakkjar fil-Maniġġar tal-Iskart.",
      "metadata": {
        "source_line_start": 14,
        "source_line_end": 18
      }
    },
    {
      "provision_ref": "s2",
      "section": "2",
      "title": "Titolu",
      "content": "(1)\nDawn\nir-regolamenti\njġibu\nfis-seħħ\niddispożizzjonijiet tad- Direttiva tal-Parlament Ewropew u talKunsill 94/62/KE tal-20 ta’ Diċembru 1994 dwar l-imballaġġ u liskart mill-imballaġġ kif emendata bid-Direttiva 2004/12/KE talParlament Ewropew u tal-Kunsill tal-11 ta’ Frar 2004 li temenda dDirettiva 94/62/KE dwar l-imballaġġ u l-iskart mill-imballaġġ, bidDirettiva 2005/20/KE tal-Parlament Ewropew u tal-Kunsill tad-9 ta’\nMarzu 2005 li temenda d-Direttiva 94/62/KE dwar l-imballaġġ u liskart mill-imballaġġ, bid-Direttiva (UE) 2015/720 tal-Parlament\nEwropew u tal-Kunsill tad-29 ta’ April 2015 li temenda d-Direttiva 94/\n62/KE rigward it-tnaqqis tal-konsum tal-basktijiet tal-plastik ħfief u\nbid-Direttiva (UE) 2018/852 tal-Parlament Ewropew u tal-Kunsill tat30 ta’ Mejju 2018 li temenda d-Direttiva 94/62/KE dwar l-imballaġġ u\nl-iskart mill-imballaġġ.\n\nSkop.\nEmendat:\nA.L. 442 tal-2012;\nA.L. 444 tal-2014.\nL.S. 549.63.\nSostitwit:\nA.L. 226 tal-2017.\nEmendat:\nA.L. 310 tal-2020;\nA.L. 152 tal-2021.\n\n(2) L-għan tad-Direttiva huwa li tarmonizza l-miżuri\nnazzjonali dwar il-ġestjoni tal-ippakkjar u l-iskart mill-ippakkjar,\nsabiex, minn naħa, jiġi evitat kwalunkwe impatt tiegħu fuq lambjent tal-Istati Membri kollha kif ukoll ta’ pajjiżi terzi jew li\njitnaqqas tali impatt biex b’hekk jiġi pprovdut livell għoli ta’\nprotezzjoni ambjentali, u, min-naħa l-oħra, sabiex jiġi żgurat ilfunzjonament tas-suq intern u jiġu evitati l-ostakoli għall-kummerċ\nu d-distorsjoni u r-restrizzjoni tal-kompetizzjoni fi ħdan l-Unjoni\nEwropea.\n(3) Dawn ir-regolamenti japplikaw għall-ippakkjar li\njitqiegħed fis-suq f ’Malta kif ukoll għall-iskart tal-ippakkjar,\nk e m m j e k k d a n h u w a w ż a t j e w m o r m i f ’ l i ve l l i n du s t r i j a l i ,\nkummerċjali, uffiċini, ħwienet, servizzi, djar jew kull livell ieħor,\nirrispettivament mill-materjal użat, sakemm l-istess ippakkjar ma\nhuwiex espressament eskluż minn dawn ir-regolamenti. Dawn irregolamenti, bl-eċċezzjoni tar-regolamenti 4, 5, 6, 7, 11, 18, u lIskeda 2, ma għandhomx japplikaw għal:\n(a) pakkeġġjar li mhuwiex intiż li jitqiegħed fis-suq Malti;\nu\n(b) produtturi li jpoġġu anqas minn 100 kilo ta’ materjal\nta’ ippakkjar u imballaġġ fis-suq f’sena kalendarja.\n(4) Dawn ir-regolamenti jistabbilixxu miżuri mmirati, bħala lewwel prijorità, lejn il-prevenzjoni tal-produzzjoni tal-iskart millippakkjar u, bħala prinċipji fundamentali addizzjonali, l-użu mill-ġdid\n\nL.S. 549.63.\n\n[ L.S.549.43\n\nL.S. 549.63.\n\nL.S. 549.134.\n\nFIL-MANIĠĠAR TAL-ISKART\n\ntal-ippakkjar, lejn ir-riċiklaġġ u lejn forom oħra tal-irkupru tal-iskart\nmill-ippakkjar u, għalhekk, lejn it-tnaqqis tal-qerda finali ta’ dan liskart sabiex tikkontribwixxi għat-tranżizzjoni lejn ekonomija\nċirkolari.\n(5) Dawn ir-regolamenti huma applikabbli mingħajr\npreġudizzju għad-dispożizzjonijiet eżistenti, u b’mod partikolari\ngħal dawk li jirrigwardaw ir-rekwiżiti dwar il-kwalità tal-ippakkjar,\nbħal ma huma dawk li jirrigwardaw is-sigurtà, il-protezzjoni tassaħħa u l-iġjene tal-prodotti ippakkjati, jew rekwiżiti eżistenti li\njirrigwardaw it-trasport, jew id-dispożizzjonijiet tar-Regolamenti\ndwar l-Iskart.\n(6) Dawn li ġejjin għandhom ikunu esklużi għall-finijiet ta’\ndawn ir-regolamenti sakemm huma koperti mir-Regolamenti dwar\nir-Riċiklaġġ tal-Kontenituri tax-Xorb:\n(a) xorb f’kontenituri tax-xorb maħsuba\nmqiegħda fuq is-suq nazzjonali; u\n\nL.S. 549.134.\n\nbiex\n\njiġu\n\n(b) kwalunkwe persuna li timporta, tqiegħed fil-fliexken\njew fil-landa jew b’xi mod ieħor timla’ x-xorb\nf’kontenituri tax-xorb maħsuba biex jiġu mqiegħda\nfuq is-suq fit-territorju Malti, hawn iżjed ’il quddiem\nimsejħa produtturi tax-xorb f’kontenituri għax-xorb:\nIżda dan ir-regolament ma jeżonerax il-prodotturi tax-xorb\nf ’ k o n t e n i t u r i t a x - x o r b m i d - d i s p o ż i z z j o n i j i e t t a ’ d a w n i rRegolamenti fir-rigward ta’ ippakkjar ieħor jew ippakkjar ta’\nmaterjal mqiegħed fuq is-suq oltre dawk il-kontenituri tax-xorb\nmsemmija fir-Regolamenti dwar ir-Riċiklaġġ tal-Kontenituri taxXorb:\nIżda wkoll ir-regolamenti 4, 5, 6, 7, 11, 18 u l-Iskeda 2\ngħandhom xorta waħda japplikaw.\n\nTifsir.\nEmendat:\nA.L. 444 tal-2014.\nA.L. 226 tal-2017.\nA.L.227 tal-2017;\nA.L. 152 tal2021;\nA.L. 369 tal-2022.\n\nL.S. 595. 28.\nKap. 549",
      "metadata": {
        "source_line_start": 19,
        "source_line_end": 119
      }
    },
    {
      "provision_ref": "s3",
      "section": "3",
      "title": "Tifsir",
      "content": "(1) F’dawn ir-regolamenti, sakemm ir-rabta tal-kliem ma\ntkunx teħtieġ xort’oħra:\n\"l-Aġenzija\" tfisser Ekonomija Ċirkulari Malta mwaqqfa bl-Ordni li\njwaqqaf l-Ekonomija Ċirkulari Malta;\n\"l-Att\" tfisser l-Att dwar il-Protezzjoni tal-Ambjent;\n\"l-awtorità kompetenti\" tfisser l-Awtorità għall-Ambjent u rRiżorsi, u tali entità jew persuna kif il-Ministru jista’ b’ordni filGazzetta jordna, u jistgħu jiġu hekk maħtura entitajiet jew persuni\ndi fferen ti bħ al a aw tori tà kom petenti g ħal dispożizzjon ijiet\ndifferenti u għal skopijiet differenti ta’ dawn ir-regolamenti;\n\"basktijiet tal-plastik\" tfisser basktijiet bi, jew mingħajr widna,\nmagħmula mill-plastik, li huma fornuti lill-konsumaturi fil-punt\ntal-bejgħ ta' oġġetti jew prodotti;\n\"basktijiet tal-plastik ħfief\" tfisser basktijiet tal-plastik bi ħxuna\nta’ inqas minn 50 mikroni;\n\"basktijiet tal-plastik ħfief ħafna\" tfisser basktijiet tal-plastik bi\nħxuna ta’ inqas minn 15 mikroni u li huma meħtieġa għal skopijiet\nta' iġjene jew ipprovduti bħala imballaġġ primarju għal ikel sfuż\nmeta dan jgħin il-prevenzjoni tal-ħela tal-ikel;\n\nFIL-MANIĠĠAR TAL-ISKART\n\n[ L.S.549.43\n\n\"basktijiet tal-plastik ossodegradabbli\" tfisser basktijiet tal-plastik\nmagħmula minn materjali tal-plastik li jinkludu addittivi li\njikkatalizzaw il-frammentazzjoni tal-materjal tal-plastik f ’mikroframmenti;\n\"bejjiegħ\" tfisser persuna li tissupplixxi bl-ippakkjar lil terzi jew\nlill-konsumatur li jkun ser juża dak l-ippakkjar, sew jekk il-mili talistess ippakkjar isir f ’dak il-waqt sew jekk ma jsirx, u l-kelma\n\"tbiegħ\" għandha tiftiehem skond dan;\n\"ċilindri tal-gass li jistgħu jerġgħu jimtlew\" tfisser ċilindri tal-gass li\njistgħu jerġgħu jimtlew użati għal tipi varji ta’ gass, iżda teskludi\nċilindri għat-tifi tan-nar;\n\"ċrieki ta’ prodotti li jinsabu f’katina magħluqa u kkontrollata\"\nt f i s s e r d a w k i ċ - ċ r i e k i f e j n i l - p r o d o t t i j i n t u ż a w f ’s i s t e m a\nkkontrollata ta’ distribuzzjoni u ta’ użu mill-ġdid tal-istess\nprodotti, f ’liema sistema jistgħu biss jitneħħew l-istess prodotti\npermezz ta’ proċedura speċifika, u f ’liema sistema jistgħu jiġu\nintrodotti biss għadd minimu ta’ prodotti li ma jkunux parti minn\ndik is-sistema;\n\"distributur\" tfisser kull persuna fiżika u legali fil-katina ta’\nprovvista, li tipprovdi l-ippakkjar, il-materjal tal-ippakkjar jew oġġetti\nppakkjati fuq bażi professjonali lill-parti li tkun ser tużahom,\nprinċipalment il-bejjiegħ bl-imnut finali jew il-konsumatur finali. Din\nit-tifsira ma tipprevjenix lil distributur milli jkun, fl-istess ħin,\nproduttur skont it-tifsira tat-terminu \"produttur\";\n\"ippakkjar imħallat\" tfisser ippakkjar magħmul minn żewġ saffi jew\naktar ta’ materjali differenti, u li ma jistax jiġi separat bl-idejn u\njifforma unità integrali waħda, li tikkonsisti minn reċipjent intern u\ninterkjużura esterna, li hija mimlija, maħżuna, trasportata u żvujtjata\nbħala tali;\n\"ippakkjar li jista’ jerġa’ jintuża\" tfisser ippakkjar li nħoloq, li ġie\nddisinjat u li tqiegħed fis-suq biex matul iċ-ċiklu tal-ħajja tiegħu\njwettaq diversi vjaġġi jew rotazzjonijiet billi jimtela mill-ġdid jew\njintuża mill-ġdid għall-istess skop li għalih kien inħoloq;\n\"intrapriża awtorizzata tal-immaniġġar tal-iskart\" tfisser\nintrapriża li hija fil-pussess ta’ permess validu maħruġ millawto rit à ko mp etent i relevan ti taħt il -l iġi jiet u rego lam enti\nnazzjonali li jirrigwardaw il-ħarsien tal-ambjent;\n\"ippakkjar\" tfisser kull prodott magħmul minn kull materjal intiż\nbiex iservi ta’ kontenitur, jew għall-protezzjoni, immaniġġar,\ntqassim jew għal preżentazzjoni ta’ prodotti mill-produttur għal dik\nil-persuna li tkun ser tuża l-prodott jew għall-konsumatur, u liema\nmaterjal jista’ jvarja minn materja prima sa prodott komplut.\nMaterjal użat għall-istess skop hawn fuq imsemmi, u li ma jkunx\nrikambjabbli, għandu wkoll jitqies bħala ippakkjar;\n\"ippakkjar\" jikkonsisti biss fi:\n(a) ippakkjar intiż għall-bejgħ ta’ prodotti jew ippakkjar\nprimarju li jkun iservi bħala ippakkjar ta’ prodott li\njkun disponibbli għall-bejgħ lill-konsumatur;\n(b) ippakkjar kollettiv jew ippakkjar sekondarju, intiż biex\n\nFIL-MANIĠĠAR TAL-ISKART\n\n[ L.S.549.43\n\njgħaqqad għadd ta’ prodotti disponibbli għallkonsumatur sew jekk l-istess ikun intiż biex jinbiegħ\nhekk lill-konsumatur jew biex jiġu mimlija mill-ġdid lixkafef fil-post tal-bejgħ; u l-prodott ikun jista’\njitneħħa mill-ippakkjar mingħajr ma tinbidel ilkaratteristika tal-prodott;\n(ċ) ippakkjar intiż għat-trasport jew ippakkjar terzjarju li\njintuħa biex jitnaqqas ir-riskju ta’ ħsara u biex\njiffaċilita l-immaniġġar u trasport ta’ numru ta’\nprodotti sew individwali kif ukoll kollettivi. Ippakkjar\ngħat-trasport ma jinkludix ippakkjar li jivjaġġa\nb’containers bit-triq, ferrovija, vapur u bl-ajru:\nIżda:\n(i)\n\nl-oġġetti għandhom jiġu kkunsidrati li huma\nippakkjar jekk jissodisfaw it-tifsira hawn qabel\nimsemmija\nmingħajr\npreġudizzju\ngħal\nfunzjonijiet l-oħra li l-ippakkjar jista’ jwettaq\nukoll, sakemm l-oġġett ma jkunx parti integrali\nminn prodott u jkun meħtieġ sabiex iżomm,\njappoġġa jew jippriżerva dak il-prodott matul leżistenza tiegħu u l-elementi kollha huma intiżi\nli jintużaw, jiġu kkunsmati jew mormija\nflimkien;\n(ii) oġġetti diżinjati u intiżi sabiex jimtlew meta\njinbiegħu u oġġetti li jistgħu jintremew\nmibjugħa, mimlija jew diżinjati u intiżi sabiex\njimtlew meta jinbiegħu għandhom jiġu\nkkunsidrati bħala ppakkjar sakemm jissodisfaw\nfunzjoni ta’ ippakkjar;\n(iii) komponenti ta’ ippakkjar u elementi anċillari\nintegrati fl-ippakkjar għandhom jiġu kkunsidrati\nbħala parti mill-ippakkjar li fih huma integrati.\nElementi anċillari imdendlin direttament ma’\nprodott, jew allaċċjati miegħu, u li jaqdu\nfunzjoni ta’ ippakkjar, għandhom jiġu\nkkunsidrati bħala ppakkjar sakemm mhumiex\nparti integrali minn dan il-prodott u l-elementi\nkollha huma intiżi li jiġu kkunsmati jew mormija\nflimkien.\nL-oġġetti elenkati fl-Iskeda 1 huma eżempji sabiex juru kif\ngħandhom jiġu applikati dawn il-kriterji;\n\"introduzzjoni intenzjonata\" tfisser l-att li tintuża apposta\nsustanza fil-formulazzjoni ta’ ippakkjar jew komponent talippakkjar fejn il-preżenza kontinwa tagħha hija mixtieqa flippakkjar finali jew komponent tal-ippakkjar finali sabiex tipprovdi\nkaratteristika speċfika jew dehra ta’ kwalità u \"introdott\nintenzjonalment\" għandha tiftiehem hekk. L-użu ta’ materjali\nriċiklati sabiex jiġu manifatturati materjali ġodda għall-ippakkjar,\nfejn xi porzjoni mill-materjali riċiklati tista’ tikkontjeni ammonti\nta’ materjali regolati, ma jitqiesx bħala introduzzjoni intenzjonata;\n\"kategoriji tal-ippakkjar\" tfisser ippakkjar magħmula mill-ħġieġ,\n\nFIL-MANIĠĠAR TAL-ISKART\n\n[ L.S.549.43\n\nmill-plastik, mill-karta u mill-kartun, metall, injam jew kwalunkwe\nmaterjal ieħor;\n\"Kumitat Konsultattiv dwar Responsabbiltà Estiża tal-Produtturi\"\njew \"Kumitat Konsultattiv EPR\" tfisser il-kumitat stabbilit taħt irregolament 5 tar-Regolamenti dwar Qafas ta’ Responsabbiltà Estiża\ntal-Produtturi;\n\"Kunsill Reġjonali\" tfisser kunsill reġjonali mwaqqaf bl-Att dwar\nGvern Lokali;\n\nKap. 363.\n\n\"id-disponibilità fis-suq\" tfisser kull fornitura ta’ ppakkjar, materjal\ntal-ippakkjar jew oġġetti ppakkjati għad-distribuzzjoni, konsum jew\nużu fis-suq f’Malta waqt it-twettiq ta’ attività kummerċjali, kemm\nb’korrispettiv ta’ ħlas kif ukoll b’xejn;\n\"il-Ministru\" tfisser il-Ministru responsabbli għall-Att dwar ilProtezzjoni tal-Ambjent u l-Att dar is-Sigurezza tal-Prodotti\nrispettivament;\n\nKap. 549.\nKap. 427.\n\n\"operatur ekonomiku\" tfisser persuna li għal skopijiet\nkummerċjali jew fil-kors tan-negozju, timporta, timmanifattura,\ntbiddel, timla, tippakkja, tbiegħ jew b’xi mod ieħor tissupplixxi lil\npersuni oħra, jew b’xi mod ieħor tqiegħed fis-suq Malti, materjal\ntal-ippakkjar jew ippakkjar, jew prodotti ppakkjati u l-kelma\n\"tipproduċi\" għandha tinftiehem skond dan;\n\"organizzazzjoni awtorizzata ta’ rkupru tal-iskart tal-ippakkjar\"\ntfisser organizzazzjoni ta’ responsabbiltà tal-produtturi kif imfissra firregolament 3 tar-Regolamenti dwar Qafas ta’ Responsabbiltà Estiża\ntal-Produtturi kif awtorizzata mill-awtorità kompetenti skont dawn irregolamenti, li l-membri tagħha, permezz ta’ dawn ir-regolamenti u ssħubija tagħhom f’dik l-organizzazzjoni, kuma eżenti minn parti minn\ndawn ir-regolamenti;\n\n\"persuna li timla’ jew li tippakkja\" tfisser persuna li tippakkja laffarijiet, u \"timla\" u \"tippakkja\" għandhom l-istess tifsira;\n\"plastik\" tfisser polimer fis-sens tal-Artikolu 3(5) tar-Regolament\n(KE) Nru 1907/2006 tal-Parlament Ewropew u tal-Kunsill, li miegħu\njistgħu jkunu żdiedu addittivi jew sustanzi oħra, u li kapaċi jiffunzjona\nbħala komponent strutturali prinċipali tal-basktijiet;\n\"preżenza inċidentali\" tfisser il-preżenza mhux intenzjonata ta’\nmetall bħala element fil-materjal tal-ippakkjar jew fl-ippakkjar;\n\"produttur\" tfisser kwalunkwe persuna fiżika jew legali li:\n(a)\n\nhija stabbilita f’Malta u timmanifattura ppakkjar jew\nmaterjal ta’ ppakkjar biex jitqiegħed fis-suq f’Malta;\n\n(b)\n\nhija stabbilita f’Malta u tqiegħed fis-suq ta’ Malta,\nfuq bażi professjonali, ippakkjar, materjal talippakkjar jew oġġetti ppakkjati, minn pajjiż terz jew\nminn Stat Membru ieħor tal-UE;\n\n(ċ) tbiegħ ippakkjar jew materjal tal-ippakkjar permezz\nta’ komunikazzjoni b’distanza kif definit firRegolamenti dwar id-Drittijiet tal-Konsumatur, 2013\ndirettament lill-konsumaturi f’Malta u hija stabbilita fi\nStat Membru ieħor tal-UE jew pajjiż terz.\n\nL.S. 378.17.\n\n[ L.S.549.43\n\nL.S. 549.63\n\nL.S. 549.63\n\nL.S. 549. 63.\n\nFIL-MANIĠĠAR TAL-ISKART\n\n\"skart tal-ippakkjar\" tfisser kull ippakkjar jewmaterjal talippakkjar kopert bit-tifsira ta’ skart fir-Regolamenti dwar l-Iskart,\niżda ma jinkludixfdalijiet mill-produzzjoni;\n\"skart tal-ippakkjar iġġenerat\" tfisser l-ammont ta’ ippakkjar li jsir\nskart skont it-tifsira tar-regolament 4 tar-Regolamenti dwar l-Iskart fitterritorju ta’ Malta, wara li jkun ġie utilizzat biex jikkontjeni,\njipproteġġi, jiġu mqandla, jiġu ikkunnsinjati u preżentati oġġetti;\n\"skart tal-ippakkjar muniċipali\" tfisser is-sehem tal-iskart millippakkjar fi skart muniċipali kif imfisser fir-Regolamenti dwar lIskart;\n\"tbiddel\" tfisser l-uu jew il-modifika ta’ ippakkjar jew materjal\ntal-ippakkjar fil-produzzjoni jew formulazzjoni tal-ippakkjar;\n\"tqegħid fis-suq\" tfisser id-disponibilità fis-suq f’Malta, għall-ewwel\ndarba, ta’ ppakkjar, materjal tal-ippakkjar jew oġġetti ppakkjati;\n\nL.S. 549.63.\n\nL.S. 549.141.\nResponsabbiltà\nestiża tal-produttur\nu rekwiżiti minimi\ngħarresponsabbiltà\nestiża ta’ produttur.\nMiżjud:\nA.L. 369 tal-2022.\nL.S. 549.141.\n\n(2) It-tifsiriet \"rimi\", \"skart\", \"maniġġar tal-iskart\", \"ġbir\", \"ġbir\nseparat\", \"prevenzjoni\", \"użu mill-ġdid\", \"trattament\", \"rkupru\" u\n\"riċiklaġġ\" għandu jkollhom l-istess tifsira mogħtija lilhom firregolament 4 tar-Regolamenti dwar l-Iskart u t-tifsira \"skema ta’\nresponsabbiltà estiża tal-produtturi\" għandu jkollha l-istess tifsira kif\nmogħtija lilha fir-Regolamenti dwar Qafas ta’ Responsabbiltà Estiża\ntal-Produtturi.",
      "metadata": {
        "source_line_start": 120,
        "source_line_end": 363
      }
    },
    {
      "provision_ref": "s3a",
      "section": "3A",
      "title": "tal-Produtturi",
      "content": "(1)\nF’konformità mar-regolament 4 tar-Regolamenti\ndwar Qafas ta’ Responsabbiltà Estiża tal-Produttur, produtturi u\nrappreżentanti awtorizzati għandhom iħallsu l-ispejjeż kollha talimmaniġġar tal-iskart tal-ippakkjar li ġej mill-ippakkjar u l-materjal\ntal-ippakkjar li jqiegħdu fis-suq f’Malta.\n(2)\nIl-kontribuzzjonijiet finanzjarji li għandhom jitħallsu\nmill-produtturi tal-ippakkjar u materjal tal-ippakkjar u r-rappreżentanti\nawtorizzati li jipparteċipaw f’organizzazzjoni awtorizzata ta’ rkupru\ntal-iskart tal-ippakkjar sabiex jikkonformaw mal-obbligi tarresponsabbiltà estiża tal-produttur għandhom ikunu maħduma, kemm\njista’ jkun possibbli, billi jittieħed kont tad-durabbilità, ir-riparabbilità,\nl-użu mill-ġdid u r-riċiklabbiltà tal-ippakkjar u l-preżenza ta’ sustanzi\nperikolużi fl-ippakkjar:\nIżda produtturi li jipparteċipaw f’organizzazzjoni\nawtorizzata ta’ rkupru tal-iskart tal-ippakkjar li jqiegħdu fis-suq ta’\nMalta ppakkjar li jista’ jerġa’ jintuża li qiegħed jerġa’ jintuża f’sistema\nkif imsemmija fis-subregolament (1) tar-regolament 10A għandhom\njiġu mitluba jħallsu tali kontribuzzjoni finanzjarja biss ma’ l-ewwel\ntqegħid fis-suq ta’ tali ppakkjar li jista’ jerġa’ jintuża:\nIżda wkoll l-imsemmija produtturi għandhom juru, għassodisfazzjon tal-Awtorità, li hemm fis-seħħ sistema ambjentalment\nsana għall-użu mill-ġdid tal-ippakkjar. Il-produtturi għandhom\njipprovdu lill-organizzazzjoni awtorizzata ta’ rkupru tal-iskart talippakkjar data dwar l-użu mill-ġdid tal-ippakkjar li jista’ jerġa’ jintuża\nskont il-formati stabbiliti mill-Awtorità.\n\nFIL-MANIĠĠAR TAL-ISKART\n\n[ L.S.549.43\n\n(3)\nBla ħsara għall-preservazzjoni tal-kunfidenzjalità ta’\ninformazzjoni kummerċjalment sensittiva f’konformità malleġiżlazzjoni\nrilevanti\ntal-Unjoni\nEwropea\nu\nnazzjonali,\norganizzazzjoni awtorizzata ta’ rkupru tal-iskart tal-ippakkjar għandha\ntagħmel disponibbli għall-pubbliku informazzjoni dwar:\n(a)\n\nis-sjieda u s-sħubija tagħha;\n\n(b)\nil-kontribuzzjonijiet finanzjarji mħallsa millmembri tagħha, dwar kull unità mibjugħa jew dwar kull\ntunnellata tal-ippakkjar jew materjal tal-ippakkjar imqiegħed\nfis-suq f’Malta; u\n(ċ)\ntal-iskart.\n\nil-proċedura ta’ għażla tal-operaturi ta’ maniġġar\n\n(4)\nBla ħsara għall-preservazzjoni tal-kunfidenzjalità ta’\ninformazzjoni kummerċjalment sensittiva f’konformità malleġiżlazzjoini rilevanti tal-Unjoni Ewropea u nazzjonali, il-Kunsilli\nReġjonali\ngħandhom\njagħmlu\ndisponibbli\ngħall-pubbliku\ninformazzjoni dwar:\n(a)\ntal-iskart;\n\nil-proċedura ta’ għażla tal-operaturi ta’ maniġġar\n\n(b)\nl-ispejjeż\nimposti\nfuq\nl-organizzazzjoni\nawtorizzata ta’ rkupru tal-iskart tal-ippakkjar għal kull\ntunnellata ta’ skart tal-ippakkjar muniċipali miġbur u ttrattat\nskont is-subregolamenti (8) u (9) tar-regolament 13; u\n(ċ)\nil-kisba tal-miri stabbiliti fl-Iskeda 3 fir-rigward\ntal-iskart tal-ippakkjar muniċipali ġġenerat fir-reġjuni tagħhom.",
      "metadata": {
        "source_line_start": 364,
        "source_line_end": 443
      }
    },
    {
      "provision_ref": "s4",
      "section": "4",
      "title": "tal-iskart tal-ippakkjar muniċipali ġġenerat fir-reġjuni tagħhom",
      "content": "(1) L-awtorità kompetenti għandha tieħu l-miżuri meħtieġa\nsabiex tiżgura li l-pakkeġġjar kollu jikkonforma mar-rekwiżiti\nessenzjali kollha kif stabbilit fir-regolamenti inkluża l-Iskeda 2:\n\nElementi essenzjali\ntal-ippakkjar.\nEmendat:\nA.L. 442 tal-2012.\n\nIżda\nl-ħtiġiet\ngħall-immanifatturar\ntal-ippakkjar\nm’għandhom fl-ebda każ japplikaw għal prodott speċfiku qabel iddata tad-dħul fis-seħħ ta’ dawn ir-regolamenti.\n(2) L-ippakkjar għandu jitqies bħala konformi mar-rekwiżiti\nessenzjali tal-Iskeda 2 kemm-il darba dan ikun konformi malistandard Malti MSA EN 13427::2004 jew MSA EN 13428::2004\njew MSA EN 13429::2004 jew MSA EN 134230::2004 jew MSA\nEN 13431::2004 jew MSA EN 13432::2004.",
      "metadata": {
        "source_line_start": 444,
        "source_line_end": 461
      }
    },
    {
      "provision_ref": "s5",
      "section": "5",
      "title": "EN 13431::2004 jew MSA EN 13432::2004",
      "content": "(1) Il-produtturi\nma\ngħandhomx\njimportaw,\njimmanifatturaw, jissupplixxu jew jużaw ippakkjar jew materjal\ntal-ippakkjar jekk il-konċentrament totali ta’ ċomb, kadmju,\nmerkurju u kromju eksavalenti preżenti f ’kull ippakkjar jew\nmaterjal tal-ippakkjar jeċċedi l-livell ta’ 100 parti kull miljun\n(ppm) fil-piż.\n(2)\n\nIl-konċentrament\n\nimsemmi\n\nfis-subregolament\n\n(1)\n\nIl-livell ta’\nkonċentrazzjoni ta’\nmetalli regolat flippakkjar.\n\nFIL-MANIĠĠAR TAL-ISKART\n\n[ L.S.549.43\n\nm’għandhux japplika f’każ ta’ ippakkjar magħmul kollu kemm hu\nm inn ċomb tal-kristall tal-ħġieġ kif definit fir-regolam enti\nrelevanti.\nDeroga għaċċestuni tal-plastik u\npalitti tal-plastik.",
      "metadata": {
        "source_line_start": 462,
        "source_line_end": 498
      }
    },
    {
      "provision_ref": "s6",
      "section": "6",
      "title": "palitti tal-plastik",
      "content": "(1) Mingħajr preġudizzju għar-regolament 5, sat-8 ta’ Frar\n2009, il-konċentrament totali ta’ ċomb, kadmju, merkurju u kromju\neksavalenti jista’ jeċċedi l-livell ta’ 100 parti kull miljun (ppm) filpiż fil-każ ta’ ċestuni tal-plastik u palitti tal-plastik li jservu bħala\nprodotti użati f’sistema kontrollata.\n(2) Iċ-ċestuni tal-plastik u l-palitti tal-plastik imsemmija fissubregolament (1) għandhom ikunu:\n(a) ġew manifatturati f’sistema ta’ riċiklaġġ ikkontrollat,\nfejn il-materjal riċiklat ikun jikkonsisti biss minn\nċestuni tal-plastik oħra jew palitti tal-plastik oħra u\nfejn l-introduzzjoni ta’ materjal estranju huwa l-inqas\nteknikament possibbli, sa massimu ta’ 20% bil-piż.\nDawk iċ-ċestuni jew palitti li jkunu ġew ritornati u li\nma jistgħux jiġu wżati mill-ġdid għandhom jiġu\nttrattati skond id-dispożizzjonijiet tal-paragrafu (b):\nIżda ħlief meta tirriżulta xi preżenza inċidentali, lebda ċomb, kadmju, merkurju jew kromju eksavalenti\nm’għandu jiġi miżjud intenzjonalment bħala element\nfl-istadju tal-manifattura jew ditribuzzjoni:\nIżda wkoll l-eċċess fil-livell ta’ konċentrament fiċċestuni u l-palitti tal-plastik li għalihom tapplika din\nid-deroga għandu jirriżulta minn żieda tal-materjal\nriċiklat;\n(b) introdotti f’sistema kontrollata ta’ distribuzzjoni u ta’\nużu mill-ġdid li jkun konformi ma’ dawn ilkondizzjonijiet:\n(i)\n\niċ-ċestuni tal-plastik u l-palitti tal-plastik ġodda\nli jkun fihom il-metall regolat, għandhom ikunu\nmmarkati b’mod permanenti u viżibbli,\n(ii) il-produttur għandu, bi qbil ma’ l-awtorità\nkompetenti, jistabbilixxi sistema ta’ inventarju,\nli tkun tinkludi sistema ta’ kontabilità\nregolatorja u finanzjara u li tkun tinkludi dawk lammonti ta’ ċestuni u palitti li jkunu ġew\nritornati lill-manifattur jew lil dik il-persuna li\ntippakkja u, jew li timla jew lil xi rappreżentant\nawtorizzat u dan biex ikun jista’ jiġi verifikat ilħarsien ta’ din id-deroga,\n(iii) kull ċestun jew palitt li jkunu ġew ritornati, u li\nma jkunux jistgħu jerġgħu jintużaw, għandhom\njiġu mormija skond proċedura speċifikament\nawtorizzata mill-awtorità kompetenti jew inkella\njiġu riċiklati permezz ta’ proċess li jkun jinkludi\nl-istess ċestuni tal-plastik jew palitti tal-plastik\nflimkien ma’ l-introduzzjoni l-inqas teknikament\npossibbli ta’ materjal estranju sa massimu ta’\n20% bil-piż,\n\nFIL-MANIĠĠAR TAL-ISKART\n(iv)\n\n(v)\n\n[ L.S.549.43\n\nil-manifattur jew ir-rappreżentant awtorizzat\ntiegħu\ngħandu\njissottometti\nlill-awtorità\nkompetenti darba fis-sena dikjarazzjoni dwar ilħarsien ta’ din id-deroga. L-istess rapport\ngħandu jinkludi kull tibdil fis-sistema u firrappreżentant awtorizzat,\nil-manifattur jew ir-rappreżentant awtorizzat\ntiegħu\ngħandu\njagħmel\ndan\nir-rapport\ndisponibbli lill-awtorità kompetenti għal perjodu\nta’ mhux inqas minn erba’ snin:\nIżda meta la l-manifattur u lanqas irrappreżentant awtorizzat tiegħu ma huma\nstabbiliti fil-Komunità, l-obbligu li ddokumentazzjoni teknika tkun disponibbli huwa\nr-responsabbilità tal-persuna li tqiegħed ilprodott fis-suq.",
      "metadata": {
        "source_line_start": 499,
        "source_line_end": 569
      }
    },
    {
      "provision_ref": "s7",
      "section": "7",
      "title": "r-responsabbilità tal-persuna li tqiegħed ilprodott fis-suq",
      "content": "Mingħajr\npreġudizzju\ngħad-dispożizzjonijiet\ntarregolament 5, il-konċentrament totali ta’ ċomb, kadmju, merkurju u\nkromju eksavalenti jista’ jeċċedi l-livell ta’ 100 parti kull miljun\n(ppm) fil-piż fil-każ ta’ ippakkjar tal-ħġieġ, kemm-il darba:\n(a) l-ebda ċomb, kadmju, merkurju jew kromju\neksavalenti m’għandu jiġi miżjud intenzjonalment flistadju tal-manifattura. Il-livell ta’ konċentrament\njista’, iżda, jeċċedi l-livelli massimi minħabba fiżżieda tal-materjal riċiklat;\n(b) fejn, matul il-kontrolli li jsiru matul perjodu ta’ tnax-il\nxahar konsekuttivi fil-produzzjoni individwali ta’ fran\nli jaħdmu l-ħġieġ, l-ammont totali ta’ konċentrament\ngħoli ta’ metalli jeċċedi l-livell ta’ 200 ppm filproduzzjoni normali u regolari, il-manifattur jew irrappreżentant awtorizzat tiegħu li jqiegħed il-prodott\nfis-suq għandu jippreżenta rapport lill-awtorità\nkompetenti;\n(ċ) ir-rapport imsemmi fil-paragrafu (b) għandu jinkludi:\n-\n\nir-riżultati tal-kontrolli,\ndeskrizzjoni tal-metodi użati fil-ġbir talinformazzjoni,\nis-sors maħsub li jkun wassal għall-preżenza ta’\nmetall fil-livell għoli ta’ konċentrament,\ndeskrizzjoni dettaljata dwar il-miżuri li jkunu\nttieħdu biex jitnaqqas il-livell għoli ta’\nkonċentrament ta’ metall:\n\nIżda meta la l-manifattur u lanqas ir-rappreżentant\nawtorizzat tiegħu ma huma stabbiliti fil-Komunità, lobbligu li d-dokumentazzjoni teknika tkun disponibbli\nhuwa r-responsabbilità tal-persuna li tqiegħed ilprodott fis-suq;\n(d) ir-riżultati tal-kontrolli fis-siti ta’ produzzjoni kif\nukoll id-deskrizzjoni tal-metodu użat fil-ġbir talinformazzjoni,\ngħandhom\njitqiegħdu\ngħad-\n\nDeroga għallippakkjar talħġieġ.\n\n[ L.S.549.43\n\nFIL-MANIĠĠAR TAL-ISKART\ndispożizzjoni tal-awtorità kompetenti f’kull waqt li\ndawn jintalbu.\n\nMiri ta’ rkupru u\nriċiklaġġ.\nEmendat:\nA.L. 226 tal-2017.\nSostitwit:\nA.L. 152 tal-2021.\nEmendat:\nA.L.452 tal-2021;\nA.L. 369 tal-2022.",
      "metadata": {
        "source_line_start": 570,
        "source_line_end": 629
      }
    },
    {
      "provision_ref": "s8",
      "section": "8",
      "title": "A.L. 369 tal-2022",
      "content": "(1)\nIl-Kunsilli Reġjonali għandhom jieħdu l-miżuri\nneċċessarji sabiex jintlaħqu l-miri stabbiliti fl-Iskeda 3 fir-rigward taliskart tal-ippakkjar muniċipali ġġenerat fir-reġjuni tagħhom.\n(1a) Produttur\nawto-konformi\njew\norganizzazzjonijiet\nawtorizzati ta’ rkupru tal-iskart tal-ippakkjar li jaġixxu f’isem\nprodutturi għandhom jieħdu l-miżuri neċessarji sabiex jintlaħqu l-miri\nstabbiliti fl-Iskeda 3 fir-rigward tal-iskart tal-ippakkjar li jirriżulta\nmill-ippakkjar intiż għat-trasport u, jew ċilindri tal-gass li jistgħu\njerġgħu jimtlew li tqiegħdu fis-suq f’Malta.\n(2)\nMingħajr preġudizzju għall-paragrafu (a) tat-taqsima 2 u talparagrafu (a) tat-taqsima 3 tal-Iskeda 3, il-Ministru jista’ jipposponi liskadenzi biex jintlaħqu l-miri msemmija fil-paragrafu (b) tat-taqsima\n2 u fil-paragrafu (b) tat-taqsima 3 tal-Iskeda 3 sa massimu ta’ ħames\nsnin, skont il-kondizzjonijiet li ġejjin:\n(a)\nid-deroga hija limitata għal massimu ta’ 15-il\npunt perċentwali minn mira unika jew maqsuma bejn żewġ\nmiri;\n(b)\nbħala riżultat tad-deroga, ir-rata ta’ riċiklaġġ\ngħal mira unika ma titnaqqasx taħt it-30%;\n(ċ)\nbħala riżultat tad-deroga, ir-rata ta’ riċiklaġġ\ngħal mira unika msemmija fil-paragrafu (b)(v) u (vi) tattaqsima 2 u fil-paragrafu (b)(v) u (vi) tat-taqsima 3 tal-Iskeda 3\nma titnaqqasx taħt is-60%; u\n\nL.S. 549.63.\n\n(d)\nsa mhux aktar tard minn erbgħa u għoxrin (24)\nxahar qabel l-iskadenza rispettiva stabbilita fil-paragrafu (b)\ntat-taqsima 2 u fil-paragrafu (b) tat-taqsima 3 tal-Iskeda 3, ilMinistru jinnotifika lill-Kummissjoni Ewropea bl-intenzjoni\ntiegħu li jipposponi l-iskadenza rispettiva u jissottometti pjan\nta’ implimentazzjoni skont l-Iskeda 15. Il-Ministru jista’\njgħaqqad dak il-pjan flimkien ma’ pjan ta’ implimentazzjoni\nsottomess konformement mar-Regolamenti dwar l-Iskart:\nIżda fi żmien tliet (3) xhur minn meta tirċievi lpjan ta’ implimentazzjoni ppreżentat, il-Kummissjoni tista’\ntitlob lil Malta tirrevedi dak il-pjan jekk il-Kummissjoni tqis li\nl-pjan ma jikkonformax mar-rekwiżiti stipulati fl-Iskeda 15.\nMalta għandha tippreżenta pjan rivedut fi żmien tliet (3) xhur\nminn meta tirċievi t-talba tal-Kummissjoni.\n(3)\nIl-ġenerazzjoni tal-iskart mill-ippakkjar f’Malta tista’\ntitqies li tkun daqs l-ammont ta’ ppakkjar li jitqiegħed fis-suq fl-istess\nsena kalendarja, fi ħdan it-territorju ta’ Malta minn kull produttur.\n\nFIL-MANIĠĠAR TAL-ISKART\n\n[ L.S.549.43\n\n(4)\nGħall-finijiet tal-kalkolu ta’ jekk intlaħqux il-miri stipulati\nfit-taqsima 2 u 3 tal-Iskeda 3:\n(a)\ngħandu jiġi kkalkulat il-piż tal-iskart millippakkjar iġġenerat u riċiklat f’sena kalendarja partikolari; u\n(b)\nil-piż tal-iskart mill-ippakkjar riċiklat għandu\njiġi kkalkulat li sar skart li, wara li jkun għadda mill-verifiki,\nis-separazzjonijiet u operazzjonijiet preliminari oħra kollha\nmeħtieġa biex jitneħħew il-materjali tal-iskart li mhumiex\nimmirati għal ipproċessar mill-ġdid sussegwenti u biex jiġi\nżgurat riċiklaġġ ta’ kwalità għolja, jidħol fl-operazzjoni ta’\nriċiklaġġ fejn il-materjali tal-iskart huma fil-fatt ipproċessati\nmill-ġdid fi prodotti, materjali jew sustanzi.\n(5)\nGħall-finijiet tas-subregolament (4)(a), il-piż tal-iskart millippakkjar riċiklat għandu jitkejjel meta l-iskart jidħol fl-operazzjoni\nta’ riċiklaġġ:\nIżda b’deroga, il-piż tal-iskart mill-ippakkjar riċiklat jista’\njitkejjel fl-output ta’ kwalunkwe operazzjoni ta’ separazzjoni:\nHekk iżda li:\n(a)\nriċiklat; u\n\ntali output ta’ skart huwa sussegwentement\n\n(b)\nil-piż tal-materjali jew tas-sustanzi li jitneħħew\nminn operazzjonijiet ulterjuri qabel l-operazzjoni ta’ riċiklaġġ\nu mhumiex sussegwentement riċiklati mhuwiex inkluż fil-piż\ntal-iskart rrappurtat bħala riċiklat.\n(6)\nL-awtorità kompetenti għandha tistabbilixxi sistema\neffettiva ta’ kontroll tal-kwalità u ta’ traċċabbiltà tal-iskart millippakkjar, sabiex tiżgura li jiġu ssodisfati l-kundizzjonijiet stipulati\nfis-subregolamenti (4)(a) u (5)(a) u (b). Sabiex tiġi żgurata\naffidabbiltà u akkuratezza tad-data miġbura dwar l-iskart millippakkjar riċiklat, is-sistema tista’ tikkonsisti minn reġistri elettroniċi\nmaħluqin skont ir-regolament 33(5) tar-Regolamenti dwar l-Iskart,\nspeċifikazzjonijiet tekniċi għar-rekwiżiti ta’ kwalità tal-iskart separat,\njew rati medji ta’ telf għall-iskart isseparat għal diversi tipi ta’ skart u\nprattiki ta’ mmaniġġjar tal-iskart rispettivament. Ir-rati medji ta’ telf\ngħandhom jintużaw biss f’każijiet fejn id-data affidabbli ma tistax\ntinkiseb b’mod ieħor u għandhom jiġu kkalkolati abbażi tar-regoli ta’\nkalkolu stabbiliti skont l-Artikolu 11a (10) tad-Direttiva 2008/98/KE.\n(7)\nGħall-finijiet tal-kalkolu ta’ jekk il-miri stipulati fit-taqsima\n2 u 3 tal-Iskeda 3 intlaħqux, l-ammont ta’ skart mill-ippakkjar\nbijodegradabbli li jsirlu trattament aerobiku u anerobiku jista’\njingħadd bħala riċiklat meta dak it-trattament jiġġenera kompost,\ndiġestat jew output ieħor bi kwantità simili ta’ kontenut riċiklat meta\n\nL.S. 549.63\n\n[ L.S.549.43\n\nFIL-MANIĠĠAR TAL-ISKART\n\nmqabbel mal-input, li għandu jintuża bħala prodott, materjal jew\nsustanza riċiklati:\nIżda meta l-output huwa użat fuq l-art, l-awtorità\nkompetenti tista’ tgħoddu bħala riċiklat biss jekk dan l-użu jirriżulta\nf’benefiċċji għall-agrikoltura jew titjib ekoloġiku.\n(8)\nL-ammont ta’ materjali tal-iskart mill-ppakkjar li waqaf\nmilli jkun skart b’riżultat ta’ operazzjoni ta’ tħejjija qabel ma jiġi\npproċessat mill-ġdid, jista’ jingħadd bħala skart riċiklat sakemm tali\nmaterjali jkunu maħsuba għal ipproċessar sussegwenti mill-ġdid fi\nprodotti, materjali jew sustanzi li huma destinati għall-użu oriġinali\njew għal skopijiet oħra:\nMadankollu, materjali tat-tmiem tal-iskart li jintużaw bħala\nfjuwils jew mezzi oħra biex tiġi ġġenerata l-enerġija, jew sabiex ikunu\ninċinerati, jintradmu jew jintremew f’landfills, ma għandhomx\njingħaddu fil-kalkolu tal-kisba tal-miri tar-riċiklaġġ.\n(9)\nGħall-finijiet tal-kalkolu ta’ jekk ikunu intlaħqu l-miri\nstipulati fit-taqsima 2 u 3 tal-Iskeda 3, jista’ jitqies ir-riċiklaġġ talmetalli separati wara l-inċinerazzjoni tal-iskart proporzjonalment massehem tal-iskart mill-ippakkjar inċinerat, sakemm il-metalli riċiklati\njilħqu l-kriterji ta’ kwalità stabbiliti fid-Deċiżjoni tal-Kummissjoni latt ta’ implimentazzjoni 2005/270 (KE) li tistabbilixxi l-formats li\njirrigwardaw is-sistema tad-database konformement mad-Direttiva\n94/62/KE tal-Parlament Ewropew u tal-Kunsill dwar l-ippakkjar u liskart mill-ippakkjar, kif emendata.\n(10) L-iskart mill-ippakkjar mibgħut lil Stat Membru ieħor\ngħall-finijiet ta’ riċiklaġġ f’dak l-Istat Membru l-ieħor jista’ jingħadd\nbiss lejn l-ilħiq tal-miri stipulati fit-taqsima 2 u 3 tal-Iskeda 3 millawtorità kompetenti fejn l-iskart mill-ippakkjar ikun inġabar.\n(11) L-iskart mill-ippakkjar esportat mill-Unjoni Ewropea\ngħandu jingħadd lejn l-ilħiq tal-miri stipulati fis-subregolamenti (1) u\n(1a) fil-każ biss li jkunu ġew sodisfatti r-rekwiżiti tas-subregolament\n(6) u jekk, skont ir-Regolament (KE) Nru 1013/2006 tal-Parlament\nEwropew u tal-Kunsill, l-esportatur jista’ jagħti prova li l-vjeġġ taliskart jikkonforma mar-rekwiżiti ta’ dak ir-Regolament u li ttrattament tal-iskart mill-ippakkjar barra mill-Unjoni Ewropea jkun\nsar f’kundizzjonijiet ġeneralment ekwivalenti għar-rekwiżiti tal-liġi\nambjentali rilevanti tal-Unjoni Ewropea.\n(12) Għall-applikazzjoni ta’ dan ir-regolament, għandhom japplikaw\nir-regoli dwar il-kalkolu, il-verifika u r-rappurtar ta’ data, b’mod\npartikolari fir-rigward tal-piż tal-iskart tal-ippakkjar iġġenerat\nstabbiliti fid-Deċiżjoni tal-Kummissjoni l-att ta’ implimentazzjoni\n2005/270 (KE) li tistabbilixxi l-formats li jirrigwardaw is-sistema taddatabase konformement mad-Direttiva 94/62/KE tal-Parlament\nEwropew u tal-Kunsill dwar l-ippakkjar u l-iskart mill-ippakkjar, kif\n\nFIL-MANIĠĠAR TAL-ISKART\n\n[ L.S.549.43\n\nemendata.\n(13) (a) Il-Kunsilli Reġjonali għandhom jissottomettu rapport\nta’ nofs is-sena lill-awtorità kompetenti fi żmien tliet (3) xhur\nkalendarji wara t-tmiem ta’ dak il-perjodu, filwaqt li rapport annwali\ngħandu jiġi sottomess lill-awtorità kompetenti fi żmien erba’ (4) xhur\nkalendarji mill-għeluq tas-sena. L-imsemmija rapporti għandhom jiġu\nsottomessi kemm f’verżjoni elettronika kif ukoll f’kopja fiżika.\n(b)\nIr-rapporti ta’ nofs is-sena u annwali għandhom jinkludu\nminn tal-inqas l-informazzjoni stabbilita fl-Iskeda 16 flimkien ma’\nkwalunkwe informazzjoni oħra li tista’ tintalab mill-awtorità\nkompetenti.\n(14)\nBla ħsara għall-kunfidenzjalità kummerċjali u\nindustrijali, kopja diġitali tar-rapporti ta’ nofs is-sena u annwali\nmsemmija fis-subregolament (13) għandha titpoġġa għaddispożizzjoni skont ir-Regolamenti dwar il-Libertà ta’ Aċċess għal\nInformazzjoni dwar l-Ambjent:\nIżda l-informazzjoni relatata mal-Parti A tal-Iskeda 16\nbiss għandha titpoġġa għad-dispożizzjoni.\n(15) Il-Kunsilli Reġjonali għandhom jużaw is-servizzi ta’\nawditur indipendenti, approvat mill-awtorita kompetenti, sabiex\njiċċertifika l-informazzjoni kollha rrapportata lill-awtorità kompetenti.\nL-awditur għandu jkun meħtieġ jiċċertifika li l-informazzjoni kollha\nrrapportata hija konformi mal-obbligi ta’ dawn ir-regolamenti:\nIżda wkoll il-Kunsilli Reġjonali għandhom jiżguraw li\ntidħol fis-seħħ proċedura tajba ta’ verifika għat-traċċabilità,\nmonitoraġġ u kontroll għall-iskart tal-ippakkjar muniċipali kollu\nmmaniġġat.\n(16) Il-Kunsilli Reġjonali għandhom jissottomettu r-rapport\nta’ verifika msemmi fis-subregolament (15) flimkien mar-rapport\nannwali msemmi fis-subregolament (13), kemm f’verżjoni elettronika\nkif ukoll f’kopja fiżika.\n(17) Il-Kunsilli Reġjonali għandhom iżommu l-informazzjoni\nmsemmija fis-subregolament (13) minn tal-inqas għal ħames (5) snin.\nL-imsemmija rekords għandhom jitpoġġew għad-dispożizzjoni fuq\ntalba tal-awtorità kompetenti.\n(18) L-Awtorità\namministrattiva fuq:\n\nkompetenti\n\ntista’\n\ntimponi\n\npenali\n\n(a)\n\nKunsill Reġjonali;\n\n(b)\n\nproduttur awto-konformi; jew\n\n(ċ)\n\norganizzazzjoni awtorizzata ta’ rkupru tal-iskart\n\nL.S. 549.39.\n\nFIL-MANIĠĠAR TAL-ISKART\n\n[ L.S.549.43\n\ntal-ippakkjar li jaġixxi f’isem produtturi li jqiegħdu fis-suq\nippakkjar intiż għat-trasport u, jew ċilindri tal-gass li jistgħu\njerġgħu jimtlew,\n\nSistemi ta’\ninformazzjoni u\nrappurtar.\nSostitwit:\nA.L. 452 tal-2021.\n\nMiżuri nazzjonali.\nEmendat:\nA.L. 442 tal-2012;\nA.L. 226 tal-2017.\nA.L.227 tal-2017;\nA.L. 152 tal-2021;\nA.L. 452 tal-2021.\n\nL.S. 549.63\n\njekk jirriżulta li fi kwalunkwe sena partikolari, kwalunkwe wieħed\nminn dawk imsemmija hawn fuq ikun naqas milli jilħaq il-minimu talmira ġenerali ta’ riċiklaġġ applikabbli stipulata fl-Iskeda 3. Limsemmija penali għandha tiġi kkalkulata skont il-mekkaniżmu\nstabbilit fl-Iskeda 17.",
      "metadata": {
        "source_line_start": 630,
        "source_line_end": 884
      }
    },
    {
      "provision_ref": "s9",
      "section": "9",
      "title": "stabbilit fl-Iskeda 17",
      "content": "L-awtorità kompetenti għandha żżomm database li jkun fih\nrecords annwali dwar l-ippakkjar u l-iskart tal-ippakkjar skont ilformat stabbilit fl-Iskeda 4 u għandha tipprovdi b’mod partikolari\ninformazzjoni dwar id-daqs, il-karatteristiċi u l-evoluzzjoni tal-flussi\ntal-imballaġġ u tal-iskart mill-imballaġġ fil-livell nazzjonali, inkluża linformazzjoni dwar it-tossiċità jew il-periklu tal-materjali talippakkjar u l-komponenti użati għall-manifattura tagħhom.",
      "metadata": {
        "source_line_start": 885,
        "source_line_end": 889
      }
    },
    {
      "provision_ref": "s10",
      "section": "10",
      "title": "informazzjoni dwar id-daqs, il-karatteristiċi u l-evoluzzjoni tal-flussi",
      "content": "(1) Il-Ministru, f’konsultazzjoni mal-awtorità kompetenti u\nmal-Aġenzija, għandu jieħu l-miżuri neċessarji sabiex (a) jiżgura li, b’żieda mal-miżuri meħudin skont irregolament 4, jiġu implimentati miżuri oħra ta’\nprevenzjoni sabiex jipprevjenu l-ġenerazzjoni ta’ skart\ntal-ippakkjar u biex jitnaqqas l-impatt tal-ippakkar fuq\nl-ambjent. Tali miżuri oħra ta’ prevenzjoni jistgħu\njikkonsistu fi programmi nazzjonali, inċentivi permezz\nta’ skemi ta’ responsabbiltà estiża ta’ produtturi biex\njitnaqqas l-impatt tal-ippakkjar fuq l-ambjent jew\nazzjonijiet simili adottati, jekk ikun xieraq, wara\nkonsultazzjoni mal-partijiet interessati bħal ma huma\noperaturi ekonomiċi, u organizzazzjonijiet talkonsumaturi u ambjentali, u maħsuba biex iġibu\nflimkien u jieħdu vantaġġ mill-ħafna inizjattivi\nmeħuda f’Malta f’dak li jirrigwarda l-prevenzjoni.\nIl-Ministru għandu jagħmel użu mill-istrumenti\nekonomiċi u miżuri oħra biex jipprovdi inċentivi għallapplikazzjoni tal-ġerarkija dwar l-iskart bħal dawk\nindikati fl-Iskeda 12 tar-Regolamenti dwar l-Iskart jew\nstrumenti u miżuri oħra xierqa;\n(b) torganizza kampanji ta’ informazzjoni għallkonsumaturi, produtturi u għal min juża l-ippakkjar\ndwar:\n(i)\n\nil-miżuri u l-miri stabbiliti f’dawn irregolamenti,\n(ii) is-sistemi disponibbli dwar ir-ritorn, ilkollezzjoni u l-irkupru,\n(iii) ir-rwol li għandhom fl-użu mill-ġdid, l-irkupru u\nr-riċiklaġġ tal-ippakkjar u tal-iskart talippakkjar,\n(iv) it-tifsira tas-sinjali u l-kitba li hemm fuq lippakkjar li hemm fis-suq,\n(v) l-elementi tal-pjani stabbiliti fis-subregolament\n\nFIL-MANIĠĠAR TAL-ISKART\n\n[ L.S.549.43\n\n(2) dwar l-immaniġġar tal-ippakkjar u l-iskart\ntal-ippakkjar;\n(vi) l-impatt ambjentali negattiv tal-konsum eċċessiv\ntal-basktijiet tal-plastik ħfief.\n(ċ) tippromwovi kampanji ta’\nkuxjenza għall-konsumatur;\n\ninformazzjoni\n\nu\n\nta’\n\n(d) tinkoraġġixxi, fejn ikun xieraq, l-irkupru tal-enerġija,\nfejn huwa preferibbli għar-riċiklar tal-materjal għal\nraġunijiet ambjentali u ta’ spejjeż. Dan jista’ jsir billi\njiġi kkunsidrat marġini suffiċjenti bejn il-miri\nnazzjonali ta’ riċiklaġġ u irkuprar;\n(e) tinkoraġġixxi, fejn ikun xieraq, l-użu ta’ materjali li\njinġiebu mill-iskart tal-ippakkjar riċiklat għallmanifattura tal-ippakkjar u prodotti oħra billi:\n(i)\n\nittejjeb il-kondizzjonijiet tas-suq għat-tali\nmaterjali;\n(ii) tirrevedi leġislazzjoni eżistenti li żżomm milli\njintużaw dawk il-materjali;\n(f)\n\ntinkoraġġixxi, fejn ikun xieraq, studji u proġetti pilota,\nli jirrigwardaw l-istrumenti ta’ prevenzjoni li ġejjin u\noħrajn:\n(i)\n\nmiżuri ta’ prevenzjoni addizzjonali biex inaqqsu\nl-impatt ambjentali tal-ippakkjar sa fejn huwa\npossibbli mingħajr ma jikkompromettu lfunzjoni essenzjali tiegħu;\n(ii) l-iżvilupp possibbli ta’ indikatur ambjentali talippakkjar biex jagħmel il-prevenzjoni tal-iskart\ntal-ippakkjar eħfef u iżjed effettiv;\n(iii) pjanijiet\ngħall-prevenzjoni\ntal-iskart\ntalippakkjar;\n(iv) l-inkoraġġiment tal-użu mill-ġdid, u b’mod\npartikolari, paragun tal-ispejjeż u l-benefiċċji\ntal-użu mill-ġdid u dawk tar-riċiklaġġ;\n(v) ir-responsabilità tal-produttur inklużi l-aspetti\nfinanzjarji.\n(ġ) tinkiseb tnaqqis sostenut fil-konsum tal-basktijiet talplastik ħfief fi ħdan it-territorju ta' Malta, permezz taladozzjoni ta' waħda jew it-tnejn ta’ dawn li ġejjin:\n(i)\n\nmiżuri li jiżguraw li l-livell ta’ konsum annwali\nma jeċċedix 90 basktijiet tal-plastik ħfief kull\npersuna sal-31 ta' Diċembru 2019 u 40 basktijiet\ntal-plastik ħfief kull persuna sal-31 ta' Diċembru\n2025, jew miri ekwivalenti stabbiliti bil-piż;\n(ii) strumenti li jiżguraw li sal-31 ta’ Diċembru\n2018, basktijiet tal-plastik ħfief ma jingħatawx\nmingħajr ħlas fil-punt tal-bejgħ tal-oġġetti jew\ntal-prodotti, ħlief jekk jiġu implimentati\nstrumenti effettivi b’mod ekwivalenti.\nMiżuri u strumenti li jridu jiġu adottati jistgħu\n\nFIL-MANIĠĠAR TAL-ISKART\n\n[ L.S.549.43\n\njinkludu l-użu ta' miri nazzjonali ta' tnaqqis,\nstrumenti ekonomiċi kif ukoll restrizzjonijiet\nkummerċjali b’deroga mir-regolament 11 ta'\ndawn ir-Regolamenti, dment li dawn irrestrizzjonijiet ikunu proporzjonati u mhux\ndiskriminatorji.\nIl-miżuri jistgħu jvarjaw skond l-impatt\nambjentali tal-basktijiet tal-plastik ħfief meta\ndawn jiġu rkuprati jew mormija, il-proprjetajiet\nta’ kompostjar tagħhom, it-tul ta’ żmien jew lużu maħsub speċifiku.\nIl-basktijiet tal-plastik ħfief ħafna jistgħu jiġu\nesklużi minn dawn il-miżuri.\n\nL.S. 549.63\n\n(2) Sabiex tilħaq l-għanijiet u l-miżuri msemmija f’dawn irregolamenti, l-awtorità kompetenti għandha tinkludi fil-pjanijiet\ngħall-immaniġġar tal-iskart meħtieġa skond id-dispożizzjonijiet tarregolament 28 tar-Regolamenti dwar l-Iskart, kapitlu speċifiku dwar\nl-immaniġġar tal-ippakkjar u tal-iskart tal-ippakkjar, li jkun jinkludi:(i)\n\nUżu mill-ġdid.\nMiżjud:\nA.L. 152 tal-2021.\nEmendat:\nA.L. 369 tal-2022.\nL.S. 549. 63.\n\nmiżuri ta’ prevenzjoni skont dan ir-regolament;\nu\n(ii)\nmiżuri xierqa biex jitnaqqas ir-rimi tal-iskart\ntal-ippakkjar fil-forma ta’ skart muniċipali mhux\nmagħżul sabiex jinkiseb livell għoli ta’ ġbir\nseparat ta’ riċiklabbli xotti, inkluż l-iskart talippakkjar.",
      "metadata": {
        "source_line_start": 890,
        "source_line_end": 1027
      }
    },
    {
      "provision_ref": "s10a",
      "section": "10A",
      "title": "separat ta’ riċiklabbli xotti, inkluż l-iskart talippakkjar",
      "content": "(1)\nF’konformità mal-ġerarkija tal-iskart stipulata firregolament 4A tar-Regolamenti dwar l-Iskart, il-Ministru, wara\nkonsultazzjoni mal-awtorità kompetenti u mal-Aġenzija, għandu jieħu\nmiżuri biex jinkoraġġixxi żieda fis-sehem ta’ ippakkjar li jista’ jerġa’\njintuża li jitqiegħed fis-suq u ta’ sistemi għall-użu mill-ġdid talimballaġġ b’mod ambjentalment korrett, mingħajr ma jikkomprometti\nl-iġjene tal-ikel jew is-sikurezza tal-konsumaturi. Dawn il-miżuri\njistgħu jinkludu, inter alia:\n(a)\n\nl-użu ta’ skemi ta’ ippakkjar ritornabbli;\n\n(b)\n\nl-istabbiliment ta’ miri kwalitattivi jew kwantitattivi;\n\n(ċ)\n\nl-użu ta’ inċentivi ekonomiċi;\n\n(d) l-istabbiliment ta’ perċentwal minimu ta’ ippakkjar li\njista’ jerġa’ jintuża li jitqiegħed fis-suq kull sena għal kull\nfluss ta’ ippakkjar.\n(2) Il-Ministru jista’ jiddeċiedi li livell aġġustat tal-miri\nmsemmija fit-taqsimiet 2 u 3 tal-Iskeda 3 għandhom jintlaħqu għal\nsena partikolari, billi jittieħed kont tas-sehem medju, fit-tliet (3)\nsnin preċedenti, tal-ippakkjar tal-bejgħ li jista’ jerġa’ jintuża\nmqiegħed fis-suq għall-ewwel darba u użat mill-ġdid bħala parti\nminn sistema sabiex l-ippakkjar jintuża mill-ġdid:\n\nFIL-MANIĠĠAR TAL-ISKART\n\n[ L.S.549.43\n\nIżda l-awtorità kompetenti tista’ tiddeċiedi li produtturi\nawto-konformi taċ-ċilindri tal-gass li jistgħu jerġgħu jimtlew, jilħqu\nlivell aġġustat tal-miri msemmija fit-taqsimiet 2 u 3 tal-Iskeda 3 għal\nsena partikolari billi jittieħed kont tas-sehem medju, fit-tliet (3) snin\npreċedenti, ta’ tali ppakkjar tal-bejgħ li jista’ jerġa’ jintuża mqiegħed\nfis-suq għall-ewwel darba u użat mill-ġdid bħala parti minn sistema\nsabiex l-ippakkjar jintuża mill-ġdid..\n(3)\nIl-livell aġġustat imsemmu fis-subegolament (2) għandu\njiġi kkalkolat billi jitnaqqas:\n(a) mill-miri stabbiliti fil-paragrafu (a) tat-taqsima 2 u filparagrafu (a) tat-taqsima 3 tal-Iskeda 3, is-sehem tal-ippakkjar\ntal-bejgħ li jista’ jerġa’ jintuża msemmi fis-subregoloament\n(2) fl-ippakkjar tal-bejgħ kollu mqiegħed fis-suq; u\n(b) mill-miri stabbiliti fil-paragrafu (b) tat-taqsima 2 u filparagrafu (b) tat-taqsima 3 tal-Iskeda 3, is-sehem tal-imballaġġ\ntal-bejgħ li jista’ jerġa’ jintuża msemmi fis-subregolament (2),\nmagħmul mill-materjal tal-ippakkjar rispettiv, fl-ippakkjar talbejgħ kollu magħmul mill-materjal imqiegħed fis-suq:\nIżda mhux aktar minn ħames punti perċentwali ta’ sehem bħal\ndan għandu jittieħed f’konsiderazzjoni għall-kalkolu tal-livell\naġġustat rispettiv.\n(4)\nL-ammonti tal-imballaġġ tal-injam li huwa msewwi għallużu mill-ġdid jistgħu jittieħu f’konsiderazzjoni għall-ksib tal-miri\nstabbiliti fil-paragrafi (a) u (b)(ii) tat-taqsima 2 u fil-paragrafi (a) u\n(b)(ii) tat-taqsima 3 tal-Iskeda 3.\n(5)\nIr-regoli għall-kalkolu stabbiliti fid-Deċiżjoni talKummissjoni l-att ta’ implimentazzjoni 2005/270 (KE) li tistabbilixxi\nl-formats li jirrigwardaw is-sistema tad-database konformement madDirettiva 94/62/KE tal-Parlament Ewropew u tal-Kunsill dwar lippakkjar u l-iskart mill-ippakkjar, kif emendata, għandhom jgħoddu\ngħas-subregolamenti (2), (3) and (4).",
      "metadata": {
        "source_line_start": 1028,
        "source_line_end": 1091
      }
    },
    {
      "provision_ref": "s11",
      "section": "11",
      "title": "għas-subregolamenti (2), (3) and (4)",
      "content": "Mingħajr preġudizzju għall-liġijiet u regolamenti oħra, lawtorità kompetenti m’għandhiex twaqqaf it-tqegħid ta’ ippakkjar\nfis-suq li jkun kompatibbli mad-dispożizzjonijiet ta’ dawn irregolamenti.\n\nId-dritt li tqiegħed\nippakkjar fis-suq.",
      "metadata": {
        "source_line_start": 1092,
        "source_line_end": 1097
      }
    },
    {
      "provision_ref": "s12",
      "section": "12",
      "title": "ippakkjar fis-suq",
      "content": "L-awtorità kompetenti tista’ tiġbor mingħand il-produtturi\ndawk il-ħlasijiet neċessarji biex tkopri l-ispejjeż talamministrazzjoni ta’ dawn ir-regolamenti.\n\nL-awtorità\nkompetenti tista’\ntitlob ħlasijiet.\n\n[ L.S.549.43\n\nIl-ġbir, ittrattament u r-rimi\ntal-iskart talippakkjar.\nEmendat:\nA.L. 442 tal-2012;\nA.L. 444 tal-2014.\nSostitwit:\nA.L. 226 tal2017;\nA.L. 152 tal2021;\nA.L. 369 tal-2022.\n\nL.S. 549.63.\n\nFIL-MANIĠĠAR TAL-ISKART",
      "metadata": {
        "source_line_start": 1098,
        "source_line_end": 1124
      }
    },
    {
      "provision_ref": "s13",
      "section": "13",
      "title": "FIL-MANIĠĠAR TAL-ISKART",
      "content": "(1)\nIl-Kunsilli Reġjonali għandhom, fir-rigward taliskart tal-ippakkjar muniċipali ġġenerat fir-reġjuni tagħhom, jużaw\nsistemi eżistenti jew jistabbilixxu sistemi ġodda, skont kwalunkwe\nliġijiet u regolamenti eżistenti, sabiex jipprovdu għal:\n(a) ġbir reġjonali bieb b’bieb tal-iskart tal-ippakkjar\nmuniċipali u t-trasport tiegħu għal intrapriżi jew\nstabbilimenti awtorizzati tal-immaniġġar tal-iskart; u\n(b) trattament tal-iskart tal-ippakkjar muniċipali kollu\nmiġbur b’mod ambjentalment san skont il-ġerarkija\ndwar l-iskart stipulata fir-regolament 4A tarRegolamenti dwar l-Iskart.\n(2)\nOrganizzazzjoni awtorizzata ta’ rkupru tal-iskart talippakkjar għandha tagħmel l-arranġamenti neċessarji mal-Kunsilli\nLokali għal:\n\nL.S. 549.63.\n\n(a) provvediment u l-manteniment ta’ recycling points\ngħall-ġbir separat, skont il-kategoriji, tal-iskart talippakkjar muniċipali ġġenerat skont il-kwota stipulata\nfir-regolament 10(2) tar-Regolamenti dwar l-Iskart.\nGħall-finijiet tar-recycling points imsemmija f’dan ilparagrafu, ġbir separat ma għandux jinkludi ġbir\nimħallat skont it-tifsira ta’ ġbir imħallat fir-regolament\n4 tar-Regolamenti dwar l-Iskart. Organizzazzjoni\nawtorizzata ta’ rkupru tal-iskart tal-ippakkjar għandha\nżżomm tali siti fi stat tajjeb u nadif f’kull ħin; u\n(b) ġbir f’waqtu tal-imsemmi skart tal-ippakkjar\nmuniċipali u t-trasport tiegħu għal intrapriżi jew\nstabbilimenti awtorizzati tal-immaniġġar tal-iskart li\nġew ingaġġati mill-organizzazzjoni awtorizzata ta’\nrkupru tal-iskart tal-ippakkjar rispettivi:\nIżda l-iskart tal-ippakkjar muniċipali miġbur\nseparatament skont il-paragrafu (a) li jiġi riċiklat għandu\njgħodd għall-kisba tal-miri rilevanti tar-riċiklaġġ mill-Kunsilli\nReġjonali. Għall-fini ta’ dan, organizzazzjoni awtorizzata ta’\nrkupru tal-iskart tal-ippakkjar għandha tipprovdi ddikjarazzjoni ffirmata msemmija fir-regolament 15 lill-Kunsill\nReġjonali rispettiv:\nIżda wkoll f’każ li l-organizzazzjonijiet\nawtorizzati ta’ rkupru tal-iskart tal-ippakkjar jonqsu milli jaslu\ngħal qbil ma’ Kunsilli Lokali partikolari, l-awtorità kompetenti,\nf’konsultazzjoni mal-Kumitat Konsultattiv EPR, għandha\ntalloka lil dawk il-Kunsilli Lokali mingħajr arranġamenti fost lorganizzazzjonijiet awtorizzati ta’ rkupru ta’ skart tal-ippakkjar\nabbażi ta’:\n(a) is-sehem fis-suq tagħhom stabbilit mill-Awtorità\nabbażi tal-metodoloġija stabbilita fl-Iskeda 18; u\n\nFIL-MANIĠĠAR TAL-ISKART\n\n[ L.S.549.43\n\n(b) il-popolazzjoni attwali ta’ dawk il-Kunsilli Lokali.\n(3)\nProdutturi awto-konformi jew terzi li jaġixxu f’isem\nprodutturi li jqiegħdu fis-suq f’Malta ippakkjar intiż għat-trasport u,\njew ċilindri tal-gass li jistgħu jerġgħu jimtlew, għandhom jiżguraw li,\nf’dak li jirrigwarda l-ippakkjar użat u l-iskart tal-ippakkjar li jirriżulta\nmill-attivitajiet tagħhom, jużaw sistemi eżistenti jew jistabbilixxu\nsistemi ġodda, individwalment jew kollettivament, jew it-tnejn, skont\nkwalunkwe liġi u regolamenti eżistenti, sabiex jipprovdu għal:\n(a) ritorn u, jew ġbir ta’ ppakkjar użat u, jew skart talippakkjar mingħand il-konsumatur, utent finali ieħor,\njew mill-fluss ta’ skart sabiex jitqiegħed fl-alternattivi\ntal-immaniġġar tal-iskart l-aktar xierqa;\n(b) użu mill-ġdid tal-ippakkjar li jista’ jerġa’ jintuża\nb’mod ambjentalment san;\n(ċ) preparazzjoni għal użu mill-ġdid jew għar-riċiklaġġ\ntal-iskart tal-ippakkjar miġbur, kif meħtieġ, bħala\nminimu, għall-kisba tal-miri stabbiliti fl-Iskeda 3.\n(4)\nGħall-finijiet sabiex jintlaħqu l-għanijiet ta’ dan irregolament, il-produtturi jew terzi li jaġixxu f’isimhom għandhom:\n(a) iwettqu kampanji ta’ informazzjoni, fejn jenfasizzaw limportanza tal-ġbir separat tal-iskart tal-ippakkjar u\njiżguraw it-trattament korrett tal-iskart tal-ippakkjar;\n(b) jipprovdu faċilitajiet adegwati fl-istabbilimenti\ntagħhom jew f’siti jew stabbilimenti oħra hekk\nidentifikati, fejn l-iskart tal-ippakkjar ikun jista’ jiġi\ndepożitat b’xejn mill-konsumatur u fejn l-iskart talippakkjar ikun jista’ jiġi milqugħ, segregat u maħżun;\n(ċ) jiżguraw li l-faċilitajiet imsemmija fil-paragrafu (b)\nikunu faċilment identifikabbli u aċċessibbli millkonsumaturi;\n(d) jagħmlu dawk l-arranġamenti meħtieġa sabiex l-iskart\ntal-ippakkjar\nmiġbur\nikun\ndisponibbli\ngħal\npreparazzjoni għall-użu mill-ġdid jew għar-riċiklaġġ.\n(5)\nIl-Kunsilli Reġjonali, il-produtturi awto-konformi jew\nterzi li jaġixxu f’isem produtturi ma għandhomx jiddisponu mill-iskart\ntal-ippakkjar miġbur mingħajr ma l-ewwel jagħmluh disponibbli għallużu mill-ġdid jew għall-irkupru li jinkludi r-riċiklaġġ.\n(6)\nIs-sistemi msemmija fis-subregolamenti (1) u (3)\ngħandhom ikunu miftuħa għall-parteċipazzjoni tal-operaturi\nekonomiċi tas-setturi kkonċernati u għall-parteċipazzjoni talawtoritajiet pubbliċi kompetenti. L-imsemmija sistemi għandhom\njapplikaw ukoll għal prodotti importati skont kondizzjonijiet tal-ebda\ndiskriminazzjoni, inkluż arranġamenti dettaljati u kwalunkwe tariffi\nimposti għall-aċċess għas-sistemi, u għandhom ikunu mfassla b’mod li\njevitaw kwalunkwe ostakolu għall-kummerċ jew distorsjoni fil-\n\n[ L.S.549.43\n\nFIL-MANIĠĠAR TAL-ISKART\n\nkompetizzjoni f’konformità mat-Trattat dwar il-Funzjonament talUnjoni Ewropea.\n(7)\nIl-miżuri msemmija fis-subregolamenti (1), (3), (4), (5) u\n(8) għandhom jagħmlu parti minn politika li tkopri l-ippakkjar u liskart mill-ippakkjar kollu u għandhom jieħdu kont, b’mod partikolari,\nir-rekwiżiti rigward il-protezzjoni tal-ambjent u tas-saħħa talkonsumatur, is-sikurezza u l-iġjene, il-protezzjoni tal-kwalità, lawtentiċità u l-karatteristiċi tekniċi tal-prodotti ppakkjati u materjali\nużati, u l-protezzjoni tad-drittijiet tal-proprjetà industrijali u\nkummerċjali.\n(8)\nOrganizzazzjoni awtorizzata ta’ rkupru tal-iskart talippakkjar għandha tiffinanzja kwalunkwe sistema stabbilità millKunsilli Reġjonali u approvata mill-Awtorità kompetenti għall-ġbir\nbieb b’bieb, it-trattament, l-irkupru u r-rimi b’mod ambjentalment san\ntal-iskart tal-ippakkjar muniċipali kollu ġġenerat skont is-sehem fissuq tagħha:\nIżda organizzazzjoni awtorizzata ta’ rkupru tal-iskart talippakkjar għandha tagħmel l-arranġamenti neċċessarji mal-Kunsilli\nReġjonali, permezz ta’ ftehimiet bil-miktub, għall-ħlas talkontribuzzjonijiet finanzjarji tagħha lejn is-sistemi msemmia hawn\nfuq. L-imsemmi ħlas għandu jiġi eżegwit skont it-termini miftiehma\nbejn il-Kunsilli Reġjonali u l-organizzazzjonijiet awtorizzati ta’ rkupru\ntal-iskart tal-ippakkjar fil-ftehimiet bil-miktub. Tali termini għandhom\njiġu debitament notifikati lill-Awtorità fi żmien xahar (1) wara li limsemmija ftehimiet bil-miktub jiġu konklużi.\nL.S. 549.149.\n\nL.S. 549.141.\n\n(9)\nBla ħsara għar-Regolamenti dwar Qafas dwar Prodotti\ntal-Plastik li Jintużaw Darba Biss, il-kontribuzzjonijiet finanzjarji\nmsemmija fis-subregolament (8) għandhom bħala minimu jkopru lispejjeż stabbiliti fis-subregolament (3)(a) tar-regolament 6 tarRegolamenti dwar Qafas ta’ Responsabbiltà Estiża tal-Produttur:\nIżda l-kontribuzzjonijiet finanzjarji mħallsa minn\norganizzazzjoni awtorizzata ta’ rkupru tal-iskart tal-ippakkjar ma\ngħandhomx jeċċedu l-ispejjeż li huma meħtieġa sabiex jiġu pprovduti\nservizzi ta’ maniġġar tal-iskart b’mod kosteffiċjenti. Tali spejjeż\ngħandhom jiġu stabbiliti b’mod trasparenti bejn l-Awtorità, il-Kunsilli\nReġjonali, l-organizzazzjonijiet awtorizzati ta’ irkupru tal-iskart talippakkjar u kwalunkwe atturi oħrajn ikkonċernati. Kwalunkwe\nreviżjoni tal-ispejjeż stabbiliti għandha tiġi kkomunikata b’avviż\nsuffiċjenti sabiex tippermetti l-organizzazzjonijiet awtorizzati ta’\nrkupru tal-iskart tal-ippakkjar jaġġustaw l-operat tagħhom għal\nkwalunkwe spejjeż riveduti:\nIżda wkoll l-imsemmija kontribuzzjonijiet finanzjarji ma\ngħandhom fl-ebda każ jinkludu kwalunkwe penali amministrattiva\nimposta mill-Awtorità fuq Kunsill Reġjonali skont is-subregolament\n\nFIL-MANIĠĠAR TAL-ISKART\n\n[ L.S.549.43\n\n(19) tar-regolament 8.\n(10) Is-sehem fis-suq imsemmi fis-subregolament (8) għandu\njkun stabbilit mill-Awtorità abbażi tal-metodoloġija stabbilita fl-Iskeda",
      "metadata": {
        "source_line_start": 1125,
        "source_line_end": 1282
      }
    },
    {
      "provision_ref": "s18",
      "section": "18",
      "title": "jkun stabbilit mill-Awtorità abbażi tal-metodoloġija stabbilita fl-Iskeda",
      "content": "(11) L-awtorità kompetenti, f’konsultazzjoni mal-Kumitat\nKonsultattiv EPR, għandha tiżgura li sal-31 ta’ Diċembru 2024 liskemi ta’ responsabbiltà estiża tal-produttur ikunu stabbiliti għallippakkjar kollu skont id-dispożizzjonijiet tar-Regolamenti dwar Qafas\nta’ Responsabbiltà Estiża tal-Produtturi.\n(12) Il-Ministru, f’konsultazzjoni mal-awtorità kompetenti u malAġenzija, għandu jieħu miżuri sabiex jippromwovi riċiklaġġ ta’\nkwalità għolja tal-iskart mill-ippakkjar u sabiex jiġu sodisfatti listandards ta’ kwalità meħtieġa għas-setturi rilevanti tar-riċiklaġġ.\nGħal dak il-għan, ir-regolament 10Ċ(1) tar-Regolamenti dwar l-Iskart\ngħandu japplika għall-iskart tal-ippakkjar, inkluż għall-ippakkjar\nimħallat.",
      "metadata": {
        "source_line_start": 1283,
        "source_line_end": 1291
      }
    },
    {
      "provision_ref": "s14",
      "section": "14",
      "title": "imħallat",
      "content": "(1) L-awtorità kompetenti għandha tagħmel stħarriġ dwar\nil- karatterizzazzjoni tal-iskart tal-ippakkjar, li jiddetermina t-tip u\nd-diżaggregazzjoni f ’perċentwali (%) tal-iskart tal-ippakkjar fliskart muniċipali.\n(2) L-istħarriġ imsemmi fis-subregolament (1) għandu jsir\nminn żmien għal żmien kull tliet (3) snin sa ħames (5) snin.\n\nL.S. 549.141.\n\nL.S. 549.63.\n\nKaratterizzazzjoni tal-Iskart\ntal-Ippakkjar.\nSostitwit:\nA.L. 226 tal-2017.\nEmendat:\nA.L. 369 tal-2022.\n\n(3) L-eżitu tal-istħarriġ dwar il-karatterizzazzjoni tal-iskart talippakkjar imsemmi fis-subregolament (1) jista’ jiġi applikat għallfinijiet sabiex:\n(a) jiġu kkalkulati r-rati attwali tal-iskart tal-ippakkjar\nirkuprat u rriċiklat skont ir-regolament 8; u\n(b) jiġu stabbiliti l-ispejjeż imsemmija fis-subregolamenti\n(8) u (9) tar-regolament 13.",
      "metadata": {
        "source_line_start": 1292,
        "source_line_end": 1313
      }
    },
    {
      "provision_ref": "s15",
      "section": "15",
      "title": "(8) u (9) tar-regolament 13",
      "content": "(1) Fil-każ tal-iskart tal-ippakkjar ittrattat f’Malta, huwa ddmir tal-Kunsilli Reġjonali, produtturi awto-konformi jew terzi li\njaġixxu f ’isem produtturi, li jiksbu dikjarazzjoni ffirmata minn\nintrapriżi jew stabbilimenti lokali tal-immaniġġar tal-iskart,\nawtorizzati mill-awtorità kompetenti skont ir-Regolamenti talIskart li tindika:\n(a)\n\nir-rata attwali li ġiet irkuprata u/jew riċiklata millfaċilità;\n\n(b)\n\nli l-iskart tal-ippakkjar ġie rkuprat jew mormi\nb’manjiera li ma tagħmilx ħsara lill-ambjent.\n\n(2) Fil-każ tal-iskart tal-ippakkjar esportat biex ikompli jiġi\nttrattat, għandu jkun id-dmir tal-Kunsilli Reġjonali, produtturi awtokonformi jew terzi li jaġixxu f’isem produtturi, li jiksbu dikjarazzjoni\nbil-miktub maħruġa mill-faċilità barranija li tirkupra u/jew\ntirriċikla l-iskart mill-ippakkjar li tindika:\n(a) ir-rata attwali li ġiet irkuprata u/jew riċiklata millfaċilità fl-Istat Membru jew fil-pajjiż terz;\n\nProva tal-irkupru\njew tar-riċiklaġġ.\nEmendat:\nA.L. 442 tal-2012.\nSostitwit:\nA.L. 226 tal-2017.\nL.S. 549.63.\nEmendat:\nA.L. 369 tal-2022.\n\n[ L.S.549.43\n\nFIL-MANIĠĠAR TAL-ISKART\n(b) li l-iskart tal-ippakkjar ġie rkuprat jew mormi\nb’manjiera li ma tagħmilx ħsara lill-ambjent.\n\n(3) Mingħajr preġudizzju għall-kunfidenzjalità kummerċjali u\nindustrijali, jekk il-Kunsilli Reġjonali, produtturi awto-konformi jew\nterzi li jaġixxu f’isem produtturi jużaw is-servizzi ta’ intrapriża jew\nstabbiliment tal-immaniġġar tal-iskart awtorizzati biex jesportaw liskart għal aktar trattament, allura din l-intrapriża jew dan listabbiliment għandhom jipprovdu l-informazzjoni msemmija fissubregolament (2) lill-produtturi jew lil terzi li jaġixxu għan-nom\ntagħhom.\n(4) L-iskart tal-ippakkjar ittrattat lokalment jew barra minn\nMalta għandu jgħodd għall-fini tal-miri tal-irkupru u tar-riċiklaġġ\nstipulati fir-regolament 8 biss jekk il-Kunsilli Reġjonali, produtturi\nawto-konformi jew terzi li jaġixxu f’isem produtturi jippreżentaw\nevidenza tal-irkupru u/jew tar-riċiklaġġ imsemmija fissubregolamenti (1) u (2) lill-awtorità kompetenti\nParteċipazzjoni fi\norganizzazzjoni\nawtorizzata ta’\nrkupru tal-iskart\ntal-ippakkjar.\nSostitwit:\nA.L. 226 tal-2017.\nEmendat:\nA.L. 152 tal2021;\nA.L. 369 tal-2022.",
      "metadata": {
        "source_line_start": 1314,
        "source_line_end": 1373
      }
    },
    {
      "provision_ref": "s16",
      "section": "16",
      "title": "A.L. 369 tal-2022",
      "content": "(1) Produttur huwa eżenti minn parti minn dawn irregolamenti kemm-il darba jkun membru ta’ organizzazzjoni ta’\nresponsabbiltà tal-produttur awtorizzata ta’ rkupru tal-iskart talippakkjar.\n(2)\nGħall-finijiet sabiex jintlaħqu l-għanijiet ta’ dawn irregolamenti b’mod kosteffiċjenti, il-produtturi huma obbligati li\njissieħbu ma’ organizzazzjoni awtorizzata tal-irkupru tal-iskart talippakkjar debitament awtorizzata mill-awtorità kompetenti għallippakkjar kollu mqiegħed fis-suq:\nIżda produtturi jistgħu jagħżlu li jkunu awto-konformi\ngħal:\n(a)\nippakkjar intiż għat-trasport li jitqiegħed fis-suq\njew is-sehem tiegħu; u, jew\n(b)\nippakkjar tal-bejgħ li jikkonsisti f’ċilindri tal-gass\nli jistgħu jerġgħu jimtlew, jekk huma juru għas-sodisfazzjon talAwtorità li hemm fis-seħħ sistemi għall-użu mill-ġdid taċċilindri tal-gass użati ambjentalment sana u l-ġestjoni\nambjentalment sana taċ-ċilindri tal-gass li saru skart.\n(3) Jekk produttur jagħżel l-awto-konformità, il-produttur huwa\nobbligat li jiffirma ftehim mad-distributur(i) biex jiġbor lura l-iskart\ntal-ippakkjar li jirriżulta minn ippakkjar intiż għat-trasport u, jew\nċilindri tal-gass li jistgħu jerġgħu jimtlew. Jekk ma jkunx hemm\nftehim, tkun meħtieġa parteċipazzjoni f’organizzazzjoni ta’ rkupru ta’\nskart għal dak l-ippakkjar kollu min-naħa tad-distributur.\n(4) Imħassar bl-Avviż Legali 369 tal-2022.\n(5) Produttur li jagħżel li jipparteċipa fi organizzazzjoni ta’\nresponsabbiltà tal-produttur awtorizzata tal-irkupru tal-iskart talippakkjar, għandu jissottometti lill-awtorità kompetenti fuq talba\ntagħha, kopja tal-ftehim iffirmat mal-operatur tal-iskema awtorizzata\n\nFIL-MANIĠĠAR TAL-ISKART\n\n[ L.S.549.43\n\ntal-irkupru tal-iskart tal-ippakkjar.",
      "metadata": {
        "source_line_start": 1374,
        "source_line_end": 1405
      }
    },
    {
      "provision_ref": "s17",
      "section": "17",
      "title": "tal-irkupru tal-iskart tal-ippakkjar",
      "content": "(1) L-operatur ta’ organizzazzjoni awtorizzata ta’ rkupru\ntal-iskart tal-ippakkjar, awtorizzata skont ir-regolament 24 għandu:\n(a) Jintrabat li jopera skont id-dispożizzjonijiet tal-liġijiet\nu regolamenti oħra, dak li jkun maqbul ma’ u f’isem ilproduttur, kif ukoll skont il-kundizzjonijiet kollha flawtorizzazzjoni maħruġa mill-awtorità kompetenti;\n(b) Għas-snin 2023 u 2024, jipprovdi sas-7 ta’ Lulju ta’ kull\nsena, lill-awtorità kompetenti dikjarazzjoni blinformazzjoni fuq l-piż ta’ ippakkjar intiż għall-bejgħ ta’\nprodotti u ippakkjar kollettiv jew materjal tal-ippakkjar\nimqiegħed fis-suq nazzjonali mill-membri tagħha waqt ilperjodu bejn l-1 ta’ Jannar sat-30 ta’ Ġunju tal-istess\nsena, skont il-format stabbillit mill-Awtorità.\n(c) Jipprovdi lill-awtorità kompetenti stqarrija ta’\nkonformità sal-31 ta’ Marzu ta’ kull sena fir-rigward\ntal-obbligi tal-irkupru u tar-riċiklaġġ skont irregolament 8 għas-sena preċedenti. Id-dispożizzjonijiet\ntal-Iskeda 12 għandhom japplikaw fir-rigward talinformazzjoni li għandha tkun inkluża fi stqarrija ta’\nkonformità;\n(d) Jipprovdi, abbażi ta’ kull tlett xhur, dikjarazzjoni, li jkun\nfiha informazzjoni dwar il-piż fattwali tal-ippakkjar jew\nmaterjal tal-ippakkjar imqiegħed fis-suq nazzjonali millmembri tal-organizzazzjoni awtorizzata tal-irkupru taliskart tal-ippakkjar matul it-tlett xhur ta’ qabel tas-sena\nkalendarja. Tali dikjarazzjoni għandha tiġi sottomessa\nlill-Awtorità, fil-format stabbilit mill-Awtorità, fi żmien\nxahar wieħed (1) wara t-tmien ta’ dak il-perjodu ta’ tlett\nxhur.\nL-informazzjoni msemmija fil-paragrafi (b) u (ċ) għandha\ntinħareġ u tiġi ffirmata minn kwalunkwe wieħed mill-firmatarji\nawtorizzati msemmija fl-Iskeda 13.\n(2) L-organizzazzjoni awtorizzata tal-irkupru tal-iskart talippakkjar għandha tippreżenta rapporti kull sitt xhur lill-awtorità\nkompetenti fi żmien tlett (3) xhur kalendarji wara t-tmiem ta’ dak\nil-perjodu, filwaqt li rapport annwali għandu jiġi ppreżentat lillawtorità kompetenti fi żmien erba’ (4) xhur kalendarji mill-għeluq\ntas-sena.\nIr-rapporti ta’ kull sitt xhur u dawk annwali għandhom\njinkludu minn tal-inqas l-informazzjoni stabbilita fit-Taqsima A u\nfit-Taqsima B tal-Iskeda 7 flimkien ma’ kwalunkwe informazzjoni\no ħ r a s p e ċ i f i k a t a f l - a w t o r i z z a z z jo n i m a ħ r u ġ a m i l l - a w t o r i t à\nkompetenti.\nIr-rapporti ta’ kull sitt xhur u dawk annwali għandhom\njinħarġu u jiġu ffirmati minn kwalunkwe wieħed mill-firmatarji\nawtorizzati msemmija fl-Iskeda 13.\n\nIt-Tħaddim ta’\norganizzazzjoni\nawtorizzata ta’\nrkupru tal-iskart\ntal-ippakkjar.\nSostitwit:\nA.L. 226 tal2017;\nEmendat:\nA.L.152 tal-2021;\nA.L. 369 tal-2022.\n\n[ L.S.549.43\n\nL.S. 549.39.\n\nFIL-MANIĠĠAR TAL-ISKART\n\n(3) Mingħajr preġudizzju għall-kunfidenzjalità kummerċjali u\nindustrijali, kopja diġitali tar-rapporti ta’ kull sitt xhur u dawk\nannwali msemmija fis-subregolament (2) għandha tkun magħmula\ndisponibbli skont ir-Regolamenti dwar il-Libertà ta’ Aċċess għal\nInformazzjoni dwar l-Ambjent:\nIżda li l-informazzjoni relatata mal-Parti A tal-Iskeda 7 biss\ntkun magħmula disponibbli.\n(4) Organizzazzjoni\nta’\nresponsabbiltà\ntal-produttur\nawtorizzata tal-irkupru tal-iskart tal-ippakkjar għandha tuża sservizzi ta’ awditur indipendenti, approvat mill-awtorita kompetenti,\nbiex jiċċertifika l-informazzjoni kollha rrapportata lill-awtorità\nkompetenti. L-awditur ikun meħtieġ li jiċċertifika li linformazzjoni kollha rrapportata hija konformi mal-obbligi ta’\ndawn ir-regolamenti u hija kif speċifikata fl-awtorizzazzjoni\nmaħruġ mill-awtorità kompetenti.\nBarra minn hekk, l-iskema awtorizzata tal-irkupru tal-iskart\ntal-ippakkjar għandha tiżgura li proċedura tajba ta’ verifika għal\ntraċċabilità, monitoraġġ u kontroll tidħol fis-seħħ għall-ippakkjar li\njista’ jerġa’ jintuża li ġie użat mill-ġdid u għall-iskart tal-ippakkjar\nkollu li jiġi ġestit.\n(5) L-iskema awtorizzata tal-irkupru tal-iskart tal-ippakkjar\ngħandha tissottometti r-rapport ta’ verifika msemmi fissubregolament (4) flimkien mar-rapport annwali msemmi fissubregolament (2).\n(6) Hija r-responsabbiltà tal-iskema awtorizzata tal-irkupru taliskart tal-ippakkjar li żżomm l-informazzjoni msemmija fissubregolamenti (1) u (2) minn tal-inqas ħames (5) snin. Dawn irrekords għandhom ikunu magħmula disponibbli fuq talba talawtorità kompetenti.\n\nSistema ta’ sinjali\nu identifikazzjoni.\nEmendat:\nA.L. 226 tal-2017.",
      "metadata": {
        "source_line_start": 1406,
        "source_line_end": 1495
      }
    },
    {
      "provision_ref": "s19",
      "section": "19",
      "title": "juża u talkonsumaturi talippakkjar",
      "content": "Kull min juża u jikkonsma l-ippakkjar, u kull min iżomm\nskart tal-ippakkjar għandu jikkopera u jipparteċipa f’kull sistema\nintiża għall-użu mill-ġdid, irkupru u riċiklaġġ tal-iskart talippakkjar. Għal dan il-għan huma għandhom jifirdu, jiddepożitaw u\njirritornaw l-ippakkjar kif mitlub minnhom.\n\nReġistru talprodutturi.\nEmendat:\nA.L. 226 tal-2017.",
      "metadata": {
        "source_line_start": 1507,
        "source_line_end": 1515
      }
    },
    {
      "provision_ref": "s20",
      "section": "20",
      "title": "A.L. 226 tal-2017",
      "content": "(1) L-awtorità kompetenti għandha żżomm u tagħmel\ndisponibbli skond dan ir-regolament reġistru li jirrigwarda lprodutturi li jirreġistraw skond ir-regolament 21 u li jkun fih l-\n\nFIL-MANIĠĠAR TAL-ISKART\n\n[ L.S.549.43\n\ninformazzjoni li tirrigwarda r-reġistrazzjoni tal-produttur kif\npreskritt fl-Iskeda 6.\n(2) L-awtorità kompetenti għandha tiżgura li r-reġistru ta’\nprodutturi jkun disponibbli għall-pubbliku mingħajr ħlas u għandha\nttella’ t-tali reġistru online fuq il-websajt tagħha.\n(3) Ir-reġistru jista’ jinżamm fi kwalunkwe forma iżda għandu\njkollu indiċi u rranġat sabiex il-membri tal-pubbliku jkunu jistgħu\njintraċċaw l-informazzjoni li jkun fih faċilment.\n(4) L-awtorità kompetenti għandha temenda l-partita relevanti\nfir-reġistru sabiex tirreġistra kull bidla għall-informazzjoni\nannotata u għandha tniżżel id-data li fiha ssir l-emenda.\n(5) Sabiex jiġi evitat id-dubju, l-ebda parti ta’ dan irregolament ma tirrikjedi li l-awtorità kompetenti għandha żżomm\nreġistru li jkun fih informazzjoni li tirrigwarda kull proċediment\nkriminali (inklużi proċedimenti retroattivi) jew kwalunkwe ħaġa li\nhija soġġetta għat-tali proċedimenti, f’kull żmien qabel ma dawk ilproċedimenti jiġu magħluqa b’mod finali.\n(6) L-ebda parti ta’ dan ir-regolament ma tirrikjedi li l-awtorità\nkompetenti żżomm informazzjoni li tkun ġiet superata minn\ninformazzjoni iżjed ġdida wara li jkunu għaddew erba’ snin minn\nmeta dik l-informazzjoni iżjed ġdida tkun iddaħħlet fir-reġistru.",
      "metadata": {
        "source_line_start": 1516,
        "source_line_end": 1545
      }
    },
    {
      "provision_ref": "s21",
      "section": "21",
      "title": "meta dik l-informazzjoni iżjed ġdida tkun iddaħħlet fir-reġistru",
      "content": "(1)Matul is-sena kalendarja li fiha jqiegħdu ppakkjar jew\nmaterjal tal-ippakkjar għall-ewwel darba fis-suq fit-territorju ta’\nMalta, il-produtturi għandhom japplikaw sabiex ikunu rreġistrati\nmal-awtorità kompetenti u għandhom jingħataw numru ta’\nreġistrazzjoni meta jirreġistraw:\nIl-produtturi għandhom juru b’mod ċar in-numru ta’\nreġistrazzjoni tagħhom fuq il-fatturi u r-riċevuti fiskali tagħhom.\n(2) Il-produtturi rreġistrati taħt is-subregolament (1) għandhom\niġeddu r-reġistrazzjoni tagħhom fuq bażi annwali mal-awtorità\nkompetenti sal-31 ta’ Marzu ta’ kull sena:\nIżda mill-1 ta’ April ta’ kull sena l-awtorità kompetenti\ngħandha taċċetta tiġdid sal-aħħar tas-sena bil-ħlas addizzjonali ta’\nmiżata ta’ sebgħin euro (€70) għal kull xahar jew parti minn xahar,\nmiżjuda mal-miżata/i preskritta/i fl-Iskeda 8.\n(3) Applikazzjoni minn produttur sabiex jirreġistra jew iġedded\nir-reġistrazzjoni għandha:\n(a)\n\nissir online jew bil-miktub;\n\n(b) tkun iffirmata minn kwalunkwe wieħed mill-firmatarji\nawtorizzati msemmija fl-Iskeda 13; u\n(ċ) tkun akkompanjata minn miżata kif preskritta fl-Iskeda",
      "metadata": {
        "source_line_start": 1546,
        "source_line_end": 1568
      }
    },
    {
      "provision_ref": "s22",
      "section": "22",
      "title": "[ L.S.549.43",
      "content": "(1)Applikazzjoni\ngħar-reġistrazzjoni\nmingħand\nilprodutturi għandha tinkludi l-informazzjoni stabbilita fil-Parti A\ntal-Iskeda 5 u dik għat-tiġdid għandha tinkludi minn tal-inqas linformazzjoni ta’ rapportar stabbilita fil-Parti B tal-Iskeda 5.\nBarra minn hekk, il-produtturi awto-konformi għandhom sa\nmhux aktar tard minn xahar minn meta jissottomettu applikazzjoni\ngħar-reġistrazzjoni jħejju pjan ta’ implimentazzjoni għal tliet snin\nli fih jispeċifikaw il-passi li għandu jieħu l-imsemmi produttur\nsabiex jikkonforma mar-rekwiżiti ta’ dawn ir-regolamenti, inklużi\nl-passi li l-produttur huwa intenzjonat li jieħu sabiex jipprevjeni\njew inaqqas l-iskart mill-ippakkjar.\nMeta jiskadi l-pjan ta’ implimentazzjoni għal tliet snin,\nproduttur awto-konformi għandu, sa mhux aktar tard minn xahar\nminn meta jippreżenta applikazzjoni għat-tiġdid, jipprovdi lillawtorità kompetenti verżjoni riveduta tal-pjan ta’ implimentazzjoni\ngħal tliet snin.\nL-awtorità kompetenti għandha tispeċifika l-format li fih\ngħandha tiġi ppreżentata l-informazzjoni u għandha toħroġ gwida\nrigward il-preżentazzjoni, l-istruttura u l-kontenut tal-pjan ta’\nimplimentazzjoni għal tliet snin.\n(2) F’każ li l-informazzjoni ppreżentata mill-produttur skont lIskeda 5 tinbidel, l-imsemmi produttur għandu jinforma lillawtorità kompetenti dwar dan sa mhux aktar tard minn xahar wara\nt-tibdil.\n(3) L-informazzjoni msemmija fis-subregolament (1) għandha\ntkun ipprovduta jew online jew bil-miktub u għandha tkun iffirmata\nminn kwalunkwe wieħed mill-firmatarji awtorizzati msemmija flIskeda 13.\n(4) Għandha tkun ir-responsabbiltà ta’ produttur reġistrat li\njżomm l-informazzjoni msemmija fis-subregolament (1) minn talinqas ħames (5) snin. Dawn ir-records għandhom ikunu magħmula\ndisponibbli fuq talba tal-awtorità kompetenti.\n(5) Meta produttur jonqos milli jipprovdi applikazzjoni sħiħa\njew jirrifjuta li jipprovdiha fi żmien xahar mid-data ta’ talba millawtorità kompetenti, l-awtorità kompetenti għandha tirrifjuta u\ntirritorna din l-applikazzjoni mhux kompluta lill-produttur.\n(6) Mingħajr preġudizzju għall-kunfidenzjalità kummerċjali u\nindustrijali, l-informazzjoni msemmija fis-subregolament (1)\ngħandha tkun magħmula disponibbli skont ir-Regolamenti dwar ilLibertà ta’ Aċċess għal Informazzjoni dwar l-Ambjent.\n(7) Produttur awto-konformi għandu juża s-servizzi ta’ awditur\nindipendenti, approvat mill-awtorita kompetenti, sabiex jiċċertifika\nli l-informazzjoni kollha rrapurtata lill-awtorità kompetenti hija\nkonformi mal-obbligazzjonijiet ta’ dawn ir-regolamenti.\n\nInformazzjoni u\nrappurtaġġ.\nEmendat:\nA.L. 442 tal-2012.\nSostitwit:\nA.L. 226 tal-2017.\nEmendat:\nA.L. 369 tal-2022.\n\n[ L.S.549.43\n\nFIL-MANIĠĠAR TAL-ISKART\n\nBarra minn hekk, il-produttur awto-konformi għandu\njiżgura li proċedura effettiva ta’ awditjar għat-traċċabilità,\nmoniteraġġ u kontroll tkun fis-seħħ għall-ippakkjar li jista’ jerġa’\njintuża li ġie użat mill-ġdid u għall-iskart tal-ippakkjar immaniġġjat.\nProduttur awto-konformi\ndispożizzjoni sakemm:\n\nhuwa\n\neżent\n\nminn\n\ntali\n\nL-imsemmi produttur jipprovdi evidenza ta’ parteċipazzjoni\nfi organizzazzjoni ta’ responsabbiltà tal-produttur(i) ċċertifikata(i)\ngħall-immaniġjar tal-ambjent skont standards internazzjonali u talUnjoni Ewropea.\nIżda wkoll li huwa jissodisfa kwalunkwe rekwiżiti li lawtorità kompetenti tista’ tintroduċi b’ rabta ma’ tali eżenzjoni.\n(8)\nProdutturi awto-konformi għandhom jissottomettu irrapport ta’ awditjar imsemmi fis-subregolament (7) meta japplikaw\nbiex iġeddu ir-reġistrazzjoni tagħhom skont is-subregolament 21(2)\nflimkien mal-informazzjoni msemmija fis-subregolament (1).\n(9) Produttur awto-konformi għandu jissottometti lill-awtorità\nkompetenti stqarrija ta’ konformità fir-rigward tal-obbligazzjonijiet\ntiegħu tal-irkupru u r-riċiklaġġ skont ir-regolament 8, meta japplika\nbiex iġedded ir-reġistrazzjoni tiegħu/tagħha skont is-subregolament\n21(2).\nId-dispożizzjonijiet tal-Iskeda 12 għandhom japplikaw firr i g w a r d t a ’ i n f o r m a z z j o n i l i g ħ an d h a t k u n f l - i s t q a r r i j a t a ’\nkonformità. Barra minn hekk, l-istqarrija ta’ konformità għandha\ntinħareġ u tiġi ffirmata minn kwalunkwe wieħed mill-firmatarji\nawtorizzati msemmija fl-Iskeda 13.\n(10) Il-produtturi jew terzi li jaġixxu f’isimhom jistgħu jipprovdu,\nfuq bażi volontarja, tali data ulterjuri li tkun disponibbli dwar lippakkjar u l-iskart tal-ippakkjar. L-imsemmija data tista’, inter alia,\ntinkludi data fuq il-produzzjoni, l-esportazzjonijiet u limportazzjonijiet ta’ ippakkjar vojt u sotto-frazzjonijiet speċifiċi talippakkjar.\n(11) L-awtorità kompetenti tista’ tqis il-problemi partikolari talintrapriżi żgħar u dawk ta’ daqs medju sabiex jipprovdu\ninformazzjoni dettaljata.\nTrasferiment tannegozju ta’\nproduttur lil ieħor.",
      "metadata": {
        "source_line_start": 1644,
        "source_line_end": 1741
      }
    },
    {
      "provision_ref": "s23",
      "section": "23",
      "title": "produttur lil ieħor",
      "content": "(1) Meta n-negozju ta’ produttur jiġi trasferit kollu jew in\np arti li ll-persun a oħ ra, il-produ ttur g ħandu ji tqies l i b aqa’\nresponsabbli għall-ippakkjar u l-materjal tal-ippakkjar li firrigward tiegħu jkun għamel applikazzjoni għar-reġistrazzjoni taħt\nir-regolament 21, sakemm ma jirnexxielux juri lill-awtorità\nkompetenti li l-persuna li lilha jkun sar it-trasferiment aċċettat li\ntissodisfa l-obbligi tal-produttur fir-rigward ta’ kull ippakkjar bħal\ndak u materjal tal-ippakkjar taħt dawn ir-regolamenti.\n(2)\n\nFejn japplika s-subregolament (1), il-persuna li lilha jkun\n\nFIL-MANIĠĠAR TAL-ISKART\n\n[ L.S.549.43\n\nġie trasferit negozju kollu jew in parti hija produttur għalliskopijiet ta’ dawn ir-regolamenti, u dik il-persuna għandha:\n(a) tapplika għar-reġistrazzjoni ma’ l-awtorità kompetenti\ntaħt ir-regolament 21; u\n(b) tobbliga ruħha li tissodisfa l-miri ta’ rkupru u riċiklaġġ\nimsemmija fir-regolament 8.",
      "metadata": {
        "source_line_start": 1742,
        "source_line_end": 1765
      }
    },
    {
      "provision_ref": "s24",
      "section": "24",
      "title": "imsemmija fir-regolament 8",
      "content": "(1) Mingħajr preġudizzju għar-Regolamenti dwar lIskart, kull persuna li tixtieq tħaddem organizzazzjoni awtorizzata\nta’ rkupru tal-iskart tal-ippakkjar kif meħtieġ taħt dawn irregolamenti, inkluż il-ġbir, l-issortjar, il-ħażna, l-esportazzjoni lirkupru u r-riċiklaġġ ta’ skart tal-ippakkjar, fuq inkarigu talprodutturi, għandha titlob u tikseb awtorizzazzjoni valida millawtorità kompetenti.\n(2) Applikazzjoni għal awtorizzazzjoni taħt is-subregolament\n(1) għandha:(a)\n\nAwtorizzazzjoni\nbiex titħaddem\norganizzazzjoni\nawtorizzata ta’\nrkupru tal-iskart\ntal-ippakkjar.\nEmendat:\nA.L. 152 tal-2021;\nA.L. 369 tal-2022.\nL.S. 549.63.\n\nissir bil-miktub;\n\n(b) tinkludi l-informazzjoni stabbilita fil-Parti A talIskeda 10;\n(ċ) tkun iffirmata minn kwalunkwe wieħed mill-firmatarji\nawtorizzati msemmija fl-Iskeda 13;\n(d) tkun akkompanjata minn miżata mhux rimborsabbli ta’\nħames mitt Euro (€500); u\n(e) tkun akkompanjata minn pjan ta’ ħidma li jipprovdi linformazzjoni msemmija fil-Parti B tal-Iskeda 10 u li\njissodisfa lill-awtorità kompetenti.\".\n(3) L-awtorità kompetenti tista’ tispeċifika l-format li fih\ngħandu jkun ippreżentat il-pjan ta’ ħidma msemmi fissubregolament (2).\n(4) Awtorizzazzjoni\nbiex\ntitħaddem\norganizzazzjoni\nawtorizzata ta’ rkupru tal-iskart tal-ippakkjar għandha tkun\nipproċessata skont l-Att.\nAwtorizzazzjoni mogħtija mill-awtorità kompetenti\ngħandha tkun soġġett għall-kundizzjonijiet inklużi flawtorizzazzjoni, fost l-oħrajn, ir-rekwiżit li s-servizzi offruti minn\norganizzazzjoni awtorizzata ta’ rkupru tal-iskart tal-ippakkjar\ngħandhom ikunu:\n(i)\n\nmiftuħa għall-parteċipazzjoni tal-produtturi kollha\nmingħajr ebda diskriminazzjoni u tali parteċipazzjoni\nm’għandhiex tkun irrifjutata jew revokata mingħajr\nġustifikazzjoni raġonevoli; u\n\n(ii) imfassla sabiex jiġi evitat kwalunkwe ostakolu għallkummerċ jew distorsjonijiet tal-kompetizzjoni skont\nir-regolamenti rilevanti.\n(5) Awtorizzazzjoni mogħtija mill-awtorità kompetenti taħt\ndawn ir-regolamenti għandha tkun valida għal perjodu ta’ żmien\niddeterminat fl-awtorizzazzjoni.\n(6)\n\nFejn\n\nikun\n\njidher\n\ngħall-awtorità\n\nkompetenti\n\nli\n\nKap. 549.\n\nFIL-MANIĠĠAR TAL-ISKART\n\n[ L.S.549.43\n\norganizzazzjoni ta’ responsabbiltà tal-produttur awtorizzata ta’\nrkupru tal-iskart tal-ippakkjar qiegħda tikser xi kundizzjoni flawtorizzazzjoni tagħha, jew li l-miri rilevanti dwar l-irkupru u rriċiklaġġ tal-iskart tal-ippakkjar, inklużi l-miri ta’ riċiklaġġ ta’\nmaterjal speċifiku, ma ntlaħqux jew mhumiex jintlaħqu, l-awtorità\nkompetenti tista’ b’deċiżjoni tirrevoka jew tibdel awtorizzazzjoni\nmogħtija taħt dan ir-regolament.\nMeta l-awtorità kompetenti tipproponi li tirrevoka jew\ntibdel awtorizzazzjoni mogħtija taħt dan ir-regolament, l-awtorità\nkompetenti għandha tibgħat avviż bil-miktub lill-iskema\nawtorizzata tal-irkupru tal-iskart tal-ippakkjar dwar id-deċiżjoni\nproposta u r-raġunijiet għaliha.\n(7) Meta awtorizzazzjoni mogħtija taħt is-subregolament (4)\nikun wasal biex jiskadi, organizzazzjoni ta’ responsabbiltà talproduttur awtorizzata tal-irkupru tal-iskart tal-ippakkjar li tixtieq\ntkompli topera bħala organizzazzjoni ta’ responsabbiltà talproduttur awtorizzata tal-irkupru tal-iskart tal-ippakkjar għandha,\nsa mhux aktar tard minn tliet (3) xhur qabel tiskadi l-awtorizzazzjoni:(a)\n\ntissottometti applikazzjoni lill-awtorità kompetenti\nsabiex iġġedded l-awtorizzazzjoni mogħtija lilha taħt\nis-subregolament (4);\n\n(b) tagħti lill-awtorità kompetenti verżjoni riveduta talpjan ta’ ħidma għat-tħaddim tal-organizzazzjoni ta’\nresponsabbiltà tal-produttur li tikkonforma mal-Parti B\ntal-Iskeda 10, iffirmata minn kwalunkwe wieħed millfirmatarji awtorizzati msemmija fl-Iskeda 13.\n(8) It-tiġdid\ntal-awtorizzazzjoni\nbiex\ntitħaddem\norganizzazzjoni awtorizzata ta’ rkupru tal-iskart tal-ippakkjar\ngħandu jkun approvat meta l-awtorità kompetenti tkun sodisfatta\nrigward il-kontenut tal-verżjoni riveduta tal-pjan ta’ ħidma\npprovdut kif meħtieġ mis-subregolament (7)(b).\n(9) Organizzazzjoni awtorizzata ta’ rkupru tal-iskart talippakkjar li tkun ingħatat awtorizzazzjoni skont is-subregolament\n(4) u (8) għandha tintalab tħallas miżata kif preskritt fl-Iskeda 11.\nProdutturi li\njqiegħdu inqas\nminn 100kg ta’\nppakjar jew\nmaterjal talippakkjar fis-suq.\nSostitwit:\nA.L. 226 tal-2017.\n\n(10) Imħassar bl-Avviż Legali 369 tal-2022.",
      "metadata": {
        "source_line_start": 1766,
        "source_line_end": 1880
      }
    },
    {
      "provision_ref": "s25",
      "section": "25",
      "title": "(10) Imħassar bl-Avviż Legali 369 tal-2022",
      "content": "(1) Produttur reġistrat li waqt l-attività tiegħu jqiegħed\ninqas minn 100kg ta’ ppakkjar jew materjal tal-ippakkjar fis-suq\nf’sena kalendarja:\n(i)\n\nm’għandux japplika għat-tiġdid bħala produttur talippakkjar jew ta’ materjal tal-ippakkjar;\n\n(ii) għandu jinforma lill-awtorità kompetenti li qed\niqiegħed inqas minn 100kg ta’ ppakkjar jew materjal\ntal-ippakkjar fis-suq, diment li l-komunikazzjoni\ntinħareġ u tkun iffirmata minn kwalunkwe wieħed\nmill-firmatarji awtorizzati msemmija fl-Iskeda 13;\n(iii) għandu jżomm l-informazzjoni msemmija fissubregolament 22(1) minn tal-inqas tliet (3) snin; u\n(iv) għandu jibqa’ responsabbli li jwettaq l-obbligi tiegħu\nta’ meta l-produttur kien qed iqiegħed aktar minn\n\nFIL-MANIĠĠAR TAL-ISKART\n\n[ L.S.549.43\n\n100kg ta’ ppakkjar jew materjal tal-ippakkjar fis-suq.\n(2) L-awtorità kompetenti għandha ttemm ir-reġistrazzjoni talproduttur imsemmija fis-subregolament (1) wara tliet (3) snin\nkalendarji:\nIżda li kwalunkwe produttur imsemmi fis-subregolament\n(1) għandu japplika għat-tiġdid bħala produttur tal-ippakkjar jew\nta’ materjal tal-ippakkjar jekk iqiegħed aktar minn 100kg ta’\nppakkjar jew materjal tal-ippakkjar fis-suq fi żmien dawk it-tliet\n(3) snin.",
      "metadata": {
        "source_line_start": 1881,
        "source_line_end": 1912
      }
    },
    {
      "provision_ref": "s26",
      "section": "26",
      "title": "(3) snin",
      "content": "(1) Bl-iskop li jilħqu l-objettivi, u jissodisfaw iddispożizzjonijiet ta’ dawn ir-regolamenti, operaturi ekonomiċi\njistgħu jidħlu fi ftehim ma’ l-awtorità kompetenti. Kull ftehim bħal\ndan għandu jispeċifika r-regoli dettaljati għall-implimentazzjoni ta’\ndawn ir-regolamenti.\n(2)\n\nFtehim.\n\nAktar minn hekk għandu:\n(a) jekk jista’ jkun jiġi infurzat kull tali ftehim bil-liġi;\n(b) jispeċifika l-objettivi ma’ l-iskadenzi ta’ żmien\nkorrispondenti;\n(ċ) ikun ippubblikat fil-Gazzetta;\n(d) ikun ikkontrollat il-ħin kollu u regolarment kull\nriżultat milħuq bil-ftehim, ikun rappurtat lillawtoritajiet kompetenti u jkun aċċessibbli għallpubbliku taħt il-kondizzjonijiet stipulati fil-ftehim;\n(e) ikun eżaminat il-progress milħuq taħt ftehim skond\ndispożizzjonijiet li jagħmlu l-awtoritajiet kompetenti.",
      "metadata": {
        "source_line_start": 1913,
        "source_line_end": 1930
      }
    },
    {
      "provision_ref": "s27",
      "section": "27",
      "title": "Ftehim",
      "content": "Persuna tkun ħatja ta’ reat taħt dawn ir-regolamenti jekk:\n(a) tonqos milli tikkonforma ruħha ma’ xi dispożizzjoni\nta’ dawn ir-regolamenti jew tonqos milli tikkonforma\nruħha mal-kondizzjonijiet tal-permess jew ma’ xi\nordni mogħtija leġittimament skond xi dispożizzjoni\nta’ dawn ir-regolamenti; jew\n(b) tikser xi restrizzjoni, projbizzjoni jew ħtieġa imposta\nminn jew taħt dawn ir-regolamenti; jew\n(ċ) taġixxi bi ksur ta’ xi dispożizzjoni ta’ dawn irregolamenti; jew\n(d) tikkonfoffa jew tittanta, jew tgħin jew tħajjar, lil xi\nħadd ieħor b’liema mezz ikun, inkluż ir-reklamar, lgħoti ta’ pariri jew ta’ flus biex jinkisru ddispożizzjonijiet ta’ dawn ir-regolamenti jew biex\npersuna tonqos milli tikkonforma ma’ dawk iddispożizzjonijiet (inkluża kull ordni leġittimament\nmogħtija skond xi dispożizzjoni ta’ dawn irregolamenti), jew biex tikser xi restrizzjoni,\nprojbizzjoni jew ħtieġa imposta minn jew taħt dawn irregolamenti.\n\nReati taħt dawn irregolamenti.\n\n[ L.S.549.43\n\nPieni.\nEmendat:\nA.L. 426 tal-2007.\n\nFIL-MANIĠĠAR TAL-ISKART",
      "metadata": {
        "source_line_start": 1931,
        "source_line_end": 1961
      }
    },
    {
      "provision_ref": "s28",
      "section": "28",
      "title": "Pieni",
      "content": "Kull min jagħmel reat taħt dawn ir-regolamenti jista’, meta\njinstab ħati, jeħel:\n(a) meta jinstab ħati għall-ewwel darba, multa ta’ mhux\nanqas minn elf u mija u erbgħa u sittin euro u disgħa u\nsittin ċenteżmu (€1,164.69) iżda mhux iżjed minn\nelfejn u tliet mija u disgħa u għoxrin euro u sebgħa u\ntletin ċenteżmu (€2,329.37);\n(b) meta jinstab ħati għat-tieni darba jew iżjed drabi,\nmulta ta’ mhux anqas minn elfejn u tliet mija u disgħa\nu għoxrin euro u sebgħa u tletin ċenteżmu (€2,329.37)\niżda mhux aktar minn erbat elef u sitt mija u tmienja u\nħamsin euro u ħamsa u sebgħin ċenteżmu (€4,658.75),\njew għall-priġunerija għal żmien mhux iżjed minn\nsentejn, jew għal dik il-multa u priġunerija flimkien:\nIżda kull meta persuna tinstab ħatja li tkun għamlet reat taħt\ndawn ir-regolamenti permezz ta’ xi vettura, sid dik il-vettura\ngħandu, meta dan ikun japplika, jinżamm responsabbli bl-istess\nmod u fl-istess grad:\nIżda wkoll il-qorti tista’ tordna lil kull min ikun instab ħati\nli għamel reat kontra dawn ir-regolamenti li jħallas dawk l-ispejjeż\nli l-awtorità kompetenti tkun għamlet u li huma msemmija f’dawn\nir-regolamenti bħala riżultat ta’ dak ir-reat, ir-revoka tal-permess\nmaħruġ mill-awtorità kompetenti u l-konfiska tal-corpus delicti,\ninkluża l-vettura jekk dan ikun japplika.\n\nApplikabilità talKodiċi Kriminali.\nKap. 9.",
      "metadata": {
        "source_line_start": 1962,
        "source_line_end": 1989
      }
    },
    {
      "provision_ref": "s29",
      "section": "29",
      "title": "Kap. 9",
      "content": "(1) Id-dispożizzjonijiet tal-artikoli 23 u 30 tal-Kodiċi\nKriminali għandhom, mutatis mutandis, ikunu japplikaw għallproċeduri dwar reati kontra dawn ir-regolamenti, hekk illi liskwalifika milli tinżamm jew tinkiseb liċenza, permess jew xi\nawtorità ma għandha fl-ebda każ tkun għal inqas minn sena.\n\nKap. 9.\n\n(2) Minkejja d-dispożizzjonijiet tal-artikolu 370 tal-Kodiċi\nKriminali, il-proċedimenti dwar reat kontra dawn ir-regolamenti\ngħandhom isiru quddiem il-Qorti tal-Maġistrati (Malta) jew ilQorti tal-Maġistrati (Għawdex), skond ma jista’ jkun il-każ, u\ngħandhom ikunu skond id-dispożizzjonijiet tal-Kodiċi Kriminali li\njirregolaw il-proċedura quddiem dawk il-qrati bħala qrati ta’\nġudikatura kriminali.\n\nKap. 9.\n\n(3) Minkejja d-dispożizzjonijiet tal-Kodiċi Kriminali, l-Avukat\nĠenerali għandu dejjem ikollu dritt ta’ appell quddiem il-Qorti talAppell Kriminali minn kull sentenza mogħtija mill-Qorti talMaġistrati (Malta) jew mill-Qorti tal-Maġistrati (Għawdex), dwar\nproċedimenti għal xi reat kontra dawn ir-regolamenti.\n\nFIL-MANIĠĠAR TAL-ISKART\n\n[ L.S.549.43\n\n[ L.S.549.43\n\nSostitwita:\nA.L. 358 tal-2013.",
      "metadata": {
        "source_line_start": 1990,
        "source_line_end": 2024
      }
    }
  ],
  "definitions": []
}
