{
  "id": "mt-sl-10-6-mlt",
  "type": "statute",
  "title": "Ordni dwar l-Ittri li bihom jintgħarfu l-Kajjikki Imħassar bl-Avviż Legali 29 tal-2001",
  "title_en": "Ordni dwar l-Ittri li bihom jintgħarfu l-Kajjikki Imħassar bl-Avviż Legali 29 tal-2001",
  "short_name": "eli/sl/10.6/mlt",
  "status": "in_force",
  "issued_date": "2010-07-22",
  "in_force_date": "2010-07-22",
  "url": "https://legislation.mt/eli/sl/10.6/20100722/mlt",
  "description": "Official text from legislation.mt (eli/sl/10.6/mlt, expression eli/sl/10.6/20100722/mlt).",
  "provisions": [
    {
      "provision_ref": "s1",
      "section": "1",
      "title": "Full text",
      "content": "I T T R I L I B I H O M JI N G Ħ A R F U L - K A J JI KK I\n\n[ L.S.10.06\n\nLEĀISLAZZJONI SUSSIDJARJA 10.06\nORDNI DWAR ITTRI LI BIHOM\nJINGĦARFU L-KAJJIKKI\n26 ta’ Settembru, 1921\nL-AVVIś TAL-PULIZIJA tas-26 ta’ Settembru, 1921.\n\nRevokat bl-AvviŜ Legali 129 tal-2001.\n\n1",
      "metadata": {
        "extraction_mode": "fallback_full_text"
      }
    }
  ],
  "definitions": []
}
