{
  "id": "mt-sl-439-3-mlt",
  "type": "statute",
  "title": "Regolamenti dwar il-Protezzjoni ta’ Annimali waqt it-Tbiċċir jew il-Qatla",
  "title_en": "Regolamenti dwar il-Protezzjoni ta’ Annimali waqt it-Tbiċċir jew il-Qatla",
  "short_name": "eli/sl/439.3/mlt",
  "status": "in_force",
  "issued_date": "2010-07-22",
  "in_force_date": "2003-09-30",
  "url": "https://legislation.mt/eli/sl/439.3/20231119/mlt",
  "description": "Official text from legislation.mt (eli/sl/439.3/mlt, expression eli/sl/439.3/20231119/mlt).",
  "provisions": [
    {
      "provision_ref": "s1",
      "section": "1",
      "title": "Disposizzjonijiet Ġenerali",
      "content": "(1) It-titolu ta’ dawn ir-regolamenti hu Regolamenti dwar\nil-Protezzjoni ta’ Annimali waqt it-Tbiċċir jew il-Qatla.\n\nTitolu u skop.\nEmendat:\nA.L. 213 tal-2023.\n\n(2) Dawn ir-regolamenti għandhom japplikaw għall-moviment,\nkenn magħluq, żamma, sturdament, qtil ta’ annimali mrobbija u\nmiżmuma għall-produzzjoni ta’ laħam, ġlud, fur jew prodotti oħra\nu għall-metodi ta’ qtil ta’ annimali għall-iskop ta’ kontroll talmard.\n(3)\n\nDawn ir-regolamenti ma japplikawx għal (a) esperimenti tekniċi jew xjentifiċi dwar il-proċeduri\nmsemmija fis-subregolament (1), imwettqa taħt issuperviżjoni tas-Servizz Veterinarju;\n(b) annimali li jinqatlu waqt attivitajiet kulturali jew\nsportivi;\n(ċ) kaċċa selvaġġa maqtula skond l-Artikolu 3 tadDirettiva tal-Kunsill ta’ l-Unjoni Ewropea 92/45/KEE.\n\n(4) L-għan ta’ dawn ir-regolamenti hu sabiex jimplimentaw irrekwiżiti tad-dispożizzjonijiet tar-Regolament tal-Kunsill (KE) Nru\n1099/2009 tal-24 ta’ Settembru 2009 dwar il-protezzjoni tal-annimali\nwaqt il-qatla u sabiex jiġu imposti multi u penalitajiet meta jkun hemm\nksur ta’ dawn ir-regolamenti.",
      "metadata": {
        "source_line_start": 13,
        "source_line_end": 35
      }
    },
    {
      "provision_ref": "s2",
      "section": "2",
      "title": "Titolu u skop",
      "content": "Għall-finijiet ta’ dawn ir-regolamenti, kemm-il darba rrabta tal-kliem ma teħtieġx xort’oħra, frażijiet u espressjonijiet użati\nf’dawn ir-regolamenti għandu jkollhom l-istess tifsira kif mogħti\nlilhom fl-Att u fir-Regolament tal-Kunsill (KE) Nru 1099/2009 tal-24\nta’ Settembru 2009 dwar il-protezzjoni tal-annimali waqt il-qatla:\n\"Att\" tfisser l-Att dwar it-Trattament Xieraq tal-Annimali;\n\nTifsir.\nSostitwit:\nA.L. 213 tal-2023.\n\nKap. 439.\n\n\"awtorità kompetenti\" tfisser is-Servizzi Veterinarji.",
      "metadata": {
        "source_line_start": 36,
        "source_line_end": 49
      }
    },
    {
      "provision_ref": "s3",
      "section": "3",
      "title": "Tifsir",
      "content": "L-annimali għandhom ikunu evitati minn kull eċitament,\nuġiegħ jew tbatija li jistgħu jiġu evitati matul il-moviment, tqegħid\nf’post ta kenn, żamma b’forza, sturdament, tbiċċir jew qatla.\n\nEvitar ta’\neċċitament, uġiegħ\nu tbatija lillannimali.\n\nKapitolu II\nĦtiġiet applikabbli għal biċċeriji",
      "metadata": {
        "source_line_start": 50,
        "source_line_end": 60
      }
    },
    {
      "provision_ref": "s4",
      "section": "4",
      "title": "Tifsir",
      "content": "Imħassrin bl-Avviż Legali 213 tal-2023.\n\nBini, faċilitajiet u\ntagħmir ta’\nbiċċeriji.\n\nL.S.439.03]\n\nPROTEZZJONI TA’ ANNIMALI WAQT IT-TBIĊĊIR JEW IL-QATLA\n\nMetodi użati għallqatla f’biċċeriji.",
      "metadata": {
        "source_line_start": 61,
        "source_line_end": 77
      }
    },
    {
      "provision_ref": "s5",
      "section": "5",
      "title": "Metodi użati għallqatla f’biċċeriji",
      "content": "Imħassrin bl-Avviż Legali 213 tal-2023.\n\nStrumenti, irbit,\ntagħmir u\nstallazzjoni użati\ngħall-isturdament u\nl-qtil.",
      "metadata": {
        "source_line_start": 78,
        "source_line_end": 87
      }
    },
    {
      "provision_ref": "s6",
      "section": "6",
      "title": "l-qtil",
      "content": "Imħassrin bl-Avviż Legali 213 tal-2023.\n\nMin jista’ jieħu\nparti fil-moviment,\nl-għoti ta’ kenn,\nirbit, sturdament,\ntbiċċir jew qtil ta’\nannimali.",
      "metadata": {
        "source_line_start": 88,
        "source_line_end": 98
      }
    },
    {
      "provision_ref": "s7",
      "section": "7",
      "title": "annimali",
      "content": "Imħassrin bl-Avviż Legali 213 tal-2023.\n\nSpezzjonijiet u\nkontrolli\nf’biċċeriji.",
      "metadata": {
        "source_line_start": 99,
        "source_line_end": 106
      }
    },
    {
      "provision_ref": "s8",
      "section": "8",
      "title": "f’biċċeriji",
      "content": "Imħassrin bl-Avviż Legali 213 tal-2023.\n\nKapitolu III\nQtil barra l-biċċeriji",
      "metadata": {
        "source_line_start": 107,
        "source_line_end": 115
      }
    },
    {
      "provision_ref": "s9",
      "section": "9",
      "title": "Applikazzjoni tarregolament 5",
      "content": "Imħassrin bl-Avviż Legali 213 tal-2023.\n\nAnnimali maqtula\ngħall-kontroll talmard.",
      "metadata": {
        "source_line_start": 116,
        "source_line_end": 122
      }
    },
    {
      "provision_ref": "s10",
      "section": "10",
      "title": "Applikazzjoni tarregolament 5",
      "content": "Imħassrin bl-Avviż Legali 213 tal-2023.\n\nQtil ta’ annimali\ngħal raġunijiet ta’\nemerġenza.",
      "metadata": {
        "source_line_start": 123,
        "source_line_end": 128
      }
    },
    {
      "provision_ref": "s11",
      "section": "11",
      "title": "Applikazzjoni tarregolament 5",
      "content": "Imħassrin bl-Avviż Legali 213 tal-2023.\n\nQtil fuq il-post ta’\nannimali feruti jew\nmorda.",
      "metadata": {
        "source_line_start": 129,
        "source_line_end": 136
      }
    },
    {
      "provision_ref": "s12",
      "section": "12",
      "title": "morda",
      "content": "Imħassrin bl-Avviż Legali 213 tal-2023.\n\nKapitolu IV\nDisposizzjonijiet Finali\nProċedura adottata\nmill-Kummissjoni\nEwropea u skond lartikolu 11 ta’ l-Att\ndwar it-Trattament\nXieraq ta’ lAnnimali.\nKap. 439.",
      "metadata": {
        "source_line_start": 137,
        "source_line_end": 149
      }
    },
    {
      "provision_ref": "s13",
      "section": "13",
      "title": "Kap. 439",
      "content": "Imħassrin bl-Avviż Legali 213 tal-2023.\n\nVerifiki fuq il-post\nminn esperti\nveterinarji.",
      "metadata": {
        "source_line_start": 150,
        "source_line_end": 155
      }
    },
    {
      "provision_ref": "s14",
      "section": "14",
      "title": "veterinarji",
      "content": "Imħassrin bl-Avviż Legali 213 tal-2023 .\n\nĊertifikat mediku\nli jakkumpanja llaħam.",
      "metadata": {
        "source_line_start": 156,
        "source_line_end": 162
      }
    },
    {
      "provision_ref": "s15",
      "section": "15",
      "title": "li jakkumpanja llaħam",
      "content": "Imħassrin bl-Avviż Legali 213 tal-2023.\n\nPiena għal min\njonqos millobbligi.\nKap. 439.\nEmendat:\nA.L. 426 ta’ l2007.\nA.L. 213 tal-2023.",
      "metadata": {
        "source_line_start": 163,
        "source_line_end": 173
      }
    },
    {
      "provision_ref": "s16",
      "section": "16",
      "title": "A.L. 213 tal-2023",
      "content": "(1) Bla ħsara għad-disposizzjonijiet ta’ dawn irregolamenti u ta’ l-Att dwar it-Trattament Xieraq ta’ l-Annimali,\npersuna li tikser xi dispossizzjoni ta’ dawn ir-regolamenti, teħel,\nmeta tinsab ħatja, multa ta’ mhux inqas minn ħdax-il elf u sitt mija\nu sitta u erbgħin euro u sebgħa u tmenin ċenteżmu (11,646.87) u\nmhux iżjed minn erbgħa u tletin elf u disa’ mija u erbgħin euro u\nsittin ċenteżmu (34,940.60).\n(2) Mingħajr\npreġudizju\ngħad-disposizzjonijiet\ntassubregolament (1), il-Qorti tista’ wkoll tordna lill-persuna ħatja li\ntkun għamlet ir-reat taħt dawn ir-regolamenti, tħallas l-ispejjeż\n\nPROTEZZJONI TA’ ANNIMALI WAQT IT-TBIĊĊIR JEW IL-QATLA [L.S.439.03\n\nmagħmula mis-Servizzi Veterinarji bħala riżultat ta’ dan ir-reat, u\nir-revoka tal-permess maħruġ taħt dawn ir-regolamenti u lkonfiska, żamma u tneħħija tal-corpus delicti.\n(3) Fejn id-Direttur tas-Servizzi Veterinarji jkollu raġuni valida\nsabiex jemmen li twettaq ksur ta’ dawn ir-regolamenti, hu għandu\njipproċedi skont l-artikolu 47 tal-Att.",
      "metadata": {
        "source_line_start": 174,
        "source_line_end": 195
      }
    },
    {
      "provision_ref": "s17",
      "section": "17",
      "title": "jipproċedi skont l-artikolu 47 tal-Att",
      "content": "L’ebda annimal miżmum jew mkabbar mhux għall-finijiet\nagrikoli ma jista’ jinqatel għall-konsum ta’ l-ikel mingħajr lawtorizzazzjoni tas-Servizzi Veterinarji.\n\nAnnimali li ma\njistgħux jinqatlu\ngħall-konsum ta’ likel.\n\nL.S.439.03]\n\nPROTEZZJONI TA’ ANNIMALI WAQT IT-TBIĊĊIR JEW IL-QATLA\n\nĦtiġiet għall-moviment u żamma ta’ annimali fi stalel fil-biċċeriji\nImħassrin bl-Avviż Legali 213 tal-2023 .\n\nIż-żamma ta’ annimali qabel ikunu storduti, mbiċċra jew maqtula\nImħassrin bl-Avviż Legali 213 tal-2023 .\n\nSKEDA Ċ\nL-isturdament jew il-qtil ta’ annimali barra mill-annimali mrobbija għall-fur\nImħassrin bl-Avviż Legali 213 tal-2023 .\n\nŻvinar ta’ annimali\nImħassrin bl-Avviż Legali 213 tal-2023 .\n\nMetodi ta’ qtil għall-kontroll tal-mard\nImħassrin bl-Avviż Legali 213 tal-2023 .\n\nMetodi biex jinqatlu annimali tal-fur\nImħassrin bl-Avviż Legali 213 tal-2023 .\n\nQtil ta’ flieles u embrijoni żejda f’hatchery waste\nImħassrin bl-Avviż Legali 213 tal-2023 .",
      "metadata": {
        "source_line_start": 196,
        "source_line_end": 239
      }
    }
  ],
  "definitions": []
}
