{
  "id": "mt-sl-161-100-mlt",
  "type": "statute",
  "title": "Direttiva mill-Ministru għall-Finanzi għall-ħruġ ta’ Euro 120,000,000 Stock tal-Gvern ta’ Malta",
  "title_en": "Direttiva mill-Ministru għall-Finanzi għall-ħruġ ta’ Euro 120,000,000 Stock tal-Gvern ta’ Malta",
  "short_name": "eli/sl/161.100/mlt",
  "status": "in_force",
  "issued_date": "2015-02-17",
  "in_force_date": "2015-02-17",
  "url": "https://legislation.mt/eli/sl/161.100/20150217/mlt",
  "description": "Official text from legislation.mt (eli/sl/161.100/mlt, expression eli/sl/161.100/20150217/mlt).",
  "provisions": [
    {
      "provision_ref": "s1",
      "section": "1",
      "title": "L-AVVIŻ LEGALI 48 tal-2015",
      "content": "It-titolu ta’ din id-direttiva hu d-Direttiva mill-Ministru\ngħall-Finanzi għall-ħruġ ta’ Euro 120,000,000 Stock tal-Gvern ta’\nMalta.",
      "metadata": {
        "source_line_start": 16,
        "source_line_end": 22
      }
    },
    {
      "provision_ref": "s2",
      "section": "2",
      "title": "Titolu",
      "content": "Għandu jinħareġ ammont ta’ Euro 120,000,000 Stock talGvern ta’ Malta kif ġej:\n\nĦruġ ta’ Stock.\n\n(a) 2% Stock tal-Gvern ta’ Malta 2020 (V) Fungibility\nIssue, u\n(b) 3% Stock tal-Gvern ta’ Malta 2040 (I), jew\n(ċ) ammonti miż-żewġ Stocks fuq imsemmija b’valur\nnominali flimkien ta’ Euro 120,000,000.",
      "metadata": {
        "source_line_start": 23,
        "source_line_end": 32
      }
    },
    {
      "provision_ref": "s3",
      "section": "3",
      "title": "Titolu",
      "content": "Il-ħruġ ta’ Stocks ser isir kif stipulat fil-prospett.\n\nMod tal-ħruġ ta’\nStocks.",
      "metadata": {
        "source_line_start": 33,
        "source_line_end": 39
      }
    },
    {
      "provision_ref": "s4",
      "section": "4",
      "title": "Stocks",
      "content": "Kull persuna u, jew enti jistgħu japplikaw għal dawn liStocks. It-tqassim tal-iStocks isir kif hemm stabbilit fil-prospett.\n\nPolicy dwar lallokazzjoni ta’\nStock.",
      "metadata": {
        "source_line_start": 40,
        "source_line_end": 45
      }
    },
    {
      "provision_ref": "s5",
      "section": "5",
      "title": "Stock",
      "content": "(1) Skont id-dispożizzjonijiet tal-Att dwar is-Swieq\nFinanzjarji, meta dawn l-iStocks jiġu allokati, għandha ssir\napplikazzjoni sabiex kull Stock jitqiegħed fuq il-lista uffiċjali u\nbiex ikun negozjat fil-Borża ta’ Malta.\n\nNegozju fil-Borża\nta’ Malta.\nKap. 345.\n\n(2) Fis-26 ta’ Marzu, 2015 wara l-pagament tal-ewwel imgħax,\nkif muri fl-artikolu 7(1)(a) u (b), kull ammont allokat skont it-2%\nStock tal-Gvern ta’ Malta 2020 (V) F.I. jiġi integrat mal-ħruġ\neżistenti ta’ dan l-iStock u wara jitqies bħala Stock wieħed.\n(3) Fil-11 ta’ Ġunju, 2015 wara l-pagament tal-ewwel imgħax,\nkif muri fl-artikolu 7(2)(a) u (b), kull ammont allokat skont it-3%\nStock tal-Gvern ta’ Malta 2040 (I) jiġi integrat u wara dawn iżżewġ Stocks jitqiesu bħala Stock wieħed.",
      "metadata": {
        "source_line_start": 46,
        "source_line_end": 61
      }
    },
    {
      "provision_ref": "s6",
      "section": "6",
      "title": "Stock",
      "content": "Is-somma ta’ flus li għandha tinġabar bl-iStocks\nimsemmija flimkien tkun ta’ Euro 120,000,000. L-Accountant\nGeneral jirriserva d-dritt li jżid is-somma li għandha tinġabar\nb’ammont ta’ mhux iżjed minn Euro 60,000,000.\n\nSomma ta’ flus li\ngħandha tinġabar.",
      "metadata": {
        "source_line_start": 62,
        "source_line_end": 70
      }
    },
    {
      "provision_ref": "s7",
      "section": "7",
      "title": "għandha tinġabar",
      "content": "(1) L-imgħax bir-rata ta’ Euro 1.00 għal kull Euro 100, tat2% Stock tal-Gvern ta’ Malta 2020 (V) jitħallas kull sitt xhur b’lura\nfis-26 ta’ Marzu u fis-26 ta’ Settembru ta’ kull sena sakemm idum\nl-iStock:\n\nRata ta’ mgħax u\ndati tal-ħlas.\n\n(a) l-ewwel ħlas pro rata tal-imgħax fuq l-ammont allokat\nmill-applikazzjonijiet sottomessi minn membri tal-\n\n[ L.S.161.100\n\nĦRUĠ TA’ EURO 120,000,000\nSTOCK TAL-GVERN TA’ MALTA\npubbliku, li jkopri il-perjodu bejn it-2 ta’ Marzu, 2015\nu l-25 ta’ Marzu, 2015 (iż-żewġ dati inklużi) jsir fis-26\nta’ Marzu, 2015;\n(b) l-ewwel ħlas pro rata tal-imgħax fuq l-ammont allokat\nmill-applikazzjonijiet b’irkant sottomessi minn\ninvestituri istituzzjonali, li jkopri l-perjodu bejn l-4 ta’\nMarzu, 2015 u l-25 ta’ Marzu, 2015 (iż-żewġ dati\ninklużi) isir fis-26 ta’ Marzu, 2015.\n\n(2) L-imgħax bir-rata ta’ Euro 1.50 għal kull Euro 100, tat-3%\nStock tal-Gvern ta’ Malta 2040 (I) jitħallas kull sitt xhur b’lura fil11 ta’ Ġunju u fil-11 ta’ Diċembru ta’ kull sena sakemm idum liStock:\n(a) l-ewwel ħlas tal-imgħax fuq l-ammont allokat millapplikazzjonijiet sottomessi minn membri talpubbliku, li jkopri il-perjodu bejn it-2 ta’ Marzu, 2015\nu l-10 ta’ Ġunju, 2015 (iż-żewġ dati inklużi) isir fil-11\nta’ Ġunju, 2015;\n(b) l-ewwel ħlas pro rata tal-imgħax fuq l-ammont allokat\nmill-applikazzjonijiet b’irkant sottomessi minn\ninvestituri istituzzjonali, li jkopri il-perjodu bejn l-4\nta’ Marzu, 2015 u l-10 ta’ Ġunju, 2015 (iż-żewġ dati\ninklużi) isir fil-11 ta’ Ġunju, 2015.\nFidwa ta’ Stock.",
      "metadata": {
        "source_line_start": 71,
        "source_line_end": 108
      }
    },
    {
      "provision_ref": "s8",
      "section": "8",
      "title": "Fidwa ta’ Stock",
      "content": "(1) It-2% Stock tal-Gvern ta’ Malta 2020 (V) jinfeda\nb’parità fis-26 ta’ Settembru, 2020.\n(2) It-3% Stock tal-Gvern ta’ Malta 2040 (I) jinfeda b’parità\nfil-11 ta’ Ġunju, 2040.",
      "metadata": {
        "source_line_start": 109,
        "source_line_end": 115
      }
    }
  ],
  "definitions": []
}
